{"meta": {"date": "2026-01-03", "version": "5.2.2+20260103"}, "data": {"code": "10E", "commander": [], "displayCommander": [], "mainBoard": [{"artist": "John Avon", "artistIds": ["798f3932-30e0-4420-aa3f-db4d613f89ca"], "availability": ["mtgo", "paper"], "boosterTypes": ["default"], "borderColor": "black", "colorIdentity": ["B"], "colors": [], "convertedManaCost": 0.0, "count": 3, "edhrecSaltiness": 0.33, "finishes": ["nonfoil", "foil"], "foreignData": [{"identifiers": {"multiverseId": "147963", "scryfallId": "052ebe7a-dd77-4ab7-8c60-77eb1cde941e"}, "language": "Chinese Simplified", "multiverseId": 147963, "name": "沼泽", "type": "基本地～沼泽", "uuid": "35464f02-0a03-5cff-91d0-4ea26dab4c6f"}, {"identifiers": {"multiverseId": "150305", "scryfallId": "2536a6fb-361b-44ba-b55f-d00875002162"}, "language": "French", "multiverseId": 150305, "name": "Marais", "type": "Terrain de base : marais", "uuid": "894b6dd9-3824-5be2-8cb7-8ec76efd373e"}, {"identifiers": {"multiverseId": "148730", "scryfallId": "aadcad4e-744d-408f-9258-65aaf35ae96e"}, "language": "German", "multiverseId": 148730, "name": "Sumpf", "type": "Standardland — Sumpf", "uuid": "ae4813d2-55b1-54b1-83f0-6cc01ca10288"}, {"identifiers": {"multiverseId": "149113", "scryfallId": "bbd34434-a760-43c3-bf8e-b605f7fbece6"}, "language": "Italian", "multiverseId": 149113, "name": "Palude", "type": "Terra Base — Palude", "uuid": "7b4dd22a-47ae-5979-894e-33f5aaa2bd80"}, {"identifiers": {"multiverseId": "148347", "scryfallId": "174876b8-64ad-4675-8f1d-27c06906b09c"}, "language": "Japanese", "multiverseId": 148347, "name": "沼", "type": "基本土地 — 沼", "uuid": "9ae4c926-7bf8-5a61-882d-846e76023e5e"}, {"identifiers": {"multiverseId": "149922", "scryfallId": "309de0b7-5304-4095-911f-a1712c37409a"}, "language": "Portuguese (Brazil)", "multiverseId": 149922, "name": "Pântano", "type": "Terreno Básico — Pântano", "uuid": "432e71fe-6b8d-5249-aacf-8abcb84a166a"}, {"identifiers": {"multiverseId": "149539", "scryfallId": "c53d9ba7-9600-472f-9b45-b4245a0f93a8"}, "language": "Russian", "multiverseId": 149539, "name": "Болото", "type": "Базовая Земля — Болото", "uuid": "f126da1e-320a-50e3-90f3-ef0778160880"}, {"identifiers": {"multiverseId": "150688", "scryfallId": "2383e951-77dc-4ce1-be5b-e6bf158ad3e2"}, "language": "Spanish", "multiverseId": 150688, "name": "Pantano", "type": "Tierra básica — Pantano", "uuid": "1f929865-26a6-58cc-8303-be325325d237"}], "frameVersion": "2003", "hasFoil": true, "hasNonFoil": true, "identifiers": {"cardKingdomFoilId": "123452", "cardKingdomId": "192570", "cardsphereFoilId": "656", "cardsphereId": "657", "deckboxId": "7512", "mcmId": "16536", "mtgjsonV4Id": "e6deab4e-8769-5bfd-8e5c-27be609daf16", "mtgoFoilId": "27267", "mtgoId": "27266", "multiverseId": "129754", "scryfallCardBackId": "0aeebaf5-8c7d-4636-9e82-8c27447861f7", "scryfallId": "f6497c73-4bbb-4923-8151-8234c98ca6d4", "scryfallIllustrationId": "49e42a5f-3347-4aa4-a600-dad810304420", "scryfallOracleId": "56719f6a-1a6c-4c0a-8d21-18f7d7350b68", "tcgplayerProductId": "15348"}, "isEtched": false, "isFoil": false, "isReprint": true, "language": "English", "layout": "normal", "legalities": {"alchemy": "Legal", "brawl": "Legal", "commander": "Legal", "duel": "Legal", "future": "Legal", "gladiator": "Legal", "historic": "Legal", "legacy": "Legal", "modern": "Legal", "oathbreaker": "Legal", "pauper": "Legal", "paupercommander": "Legal", "penny": "Legal", "pioneer": "Legal", "predh": "Legal", "premodern": "Legal", "standard": "Legal", "standardbrawl": "Legal", "timeless": "Legal", "vintage": "Legal"}, "manaValue": 0.0, "name": "Swamp", "number": "372", "originalText": "B", "printings": ["10E", "2ED", "2XM", "30A", "3ED", "40K", "4BB", "4ED", "5ED", "6ED", "7ED", "8ED", "9ED", "ACR", "AFR", "AKH", "AKR", "ALA", "ANA", "ANB", "ARC", "ATH", "AVR", "BBD", "BFZ", "BLB", "BRB", "BRC", "BRO", "BTD", "C13", "C14", "C15", "C16", "C17", "C18", "C19", "CED", "CEI", "CHK", "CLB", "CLU", "CM2", "CMA", "CMD", "CMM", "CST", "DDC", "DDD", "DDE", "DDH", "DDJ", "DDK", "DDM", "DDN", "DDP", "DDQ", "DDR", "DFT", "DKM", "DMR", "DMU", "DOM", "DPA", "DSK", "DTK", "DVD", "E01", "ELD", "EOE", "FBB", "FDN", "FIC", "FIN", "FRF", "G17", "GK1", "GK2", "GN2", "GN3", "GNT", "GRN", "GVL", "H09", "HBG", "HOP", "HOU", "ICE", "IKO", "INR", "INV", "ISD", "ITP", "J14", "J22", "J25", "JMP", "KHM", "KLD", "KLR", "KTK", "LCI", "LEA", "LEB", "LRW", "LTR", "M10", "M11", "M12", "M13", "M14", "M15", "M19", "M20", "M21", "MBS", "MD1", "ME1", "ME3", "MH2", "MH3", "MID", "MIR", "MKM", "MMQ", "MOM", "MRD", "NEO", "NPH", "ODY", "OLEP", "ONE", "ONS", "ORI", "OTJ", "P02", "P23", "PAL00", "PAL01", "PAL03", "PAL04", "PAL05", "PAL06", "PAL99", "PALP", "PANA", "PARL", "PC2", "PCA", "PD3", "PELP", "PF19", "PF20", "PGPX", "PGRU", "PHUK", "PIP", "PLST", "PMPS", "PMPS06", "PMPS07", "PMPS08", "PMPS09", "PMPS10", "PMPS11", "POR", "PPP1", "PRM", "PRW2", "PRWK", "PS11", "PSAL", "PSS2", "PSS3", "PSS4", "PTC", "PTK", "RAV", "REX", "RIX", "RNA", "ROE", "RQS", "RTR", "S99", "SCD", "SHM", "SIR", "SLD", "SLP", "SNC", "SOI", "SOM", "SPM", "STX", "SUM", "TD0", "TD2", "TDM", "THB", "THS", "TLA", "TMP", "TMT", "TPR", "TSP", "UGL", "UND", "UNF", "UNH", "USG", "UST", "VOW", "WAR", "WC01", "WC02", "WC03", "WC97", "WC98", "WC99", "WHO", "WOE", "XANA", "XLN", "ZEN", "ZNR"], "purchaseUrls": {"cardKingdom": "https://mtgjson.com/links/a9b3ddef9520f72f", "cardKingdomFoil": "https://mtgjson.com/links/009e1320af197113", "tcgplayer": "https://mtgjson.com/links/c26d8a8fc3137367"}, "rarity": "common", "setCode": "10E", "sourceProducts": {"foil": ["c5cd29de-5ec9-5e13-b8eb-40e3a9f79f9a", "c690e178-661d-5e17-9b29-a5bf6319a844"], "nonfoil": ["3f1c2aba-e5f1-5ef8-8fd8-f5942fbd5aff", "4831adbb-c0af-5d27-b407-19f2f7805949", "c690e178-661d-5e17-9b29-a5bf6319a844", "ff67afca-f016-5399-83b0-9f9f6e14f950"]}, "subtypes": ["Swamp"], "supertypes": ["Basic"], "text": "({T}: Add {B}.)", "type": "Basic Land — Swamp", "types": ["Land"], "uuid": "ec72e59f-bc37-50fd-a1b5-3afac5a402b3", "variations": ["4b3673bc-4f31-5877-9710-44d875dcca8a", "3e951ede-39fc-58c6-8a89-e2c320902ddd", "eedae11d-cb7c-5b59-bcdd-419e3d6311a1"]}, {"artist": "Ron Spencer", "artistIds": ["dab52c11-0564-4207-a4a1-c1735c946a65"], "availability": ["mtgo", "paper"], "boosterTypes": ["default"], "borderColor": "black", "colorIdentity": ["B"], "colors": [], "convertedManaCost": 0.0, "count": 3, "edhrecSaltiness": 0.33, "finishes": ["nonfoil", "foil"], "foreignData": [{"identifiers": {"multiverseId": "147964", "scryfallId": "e1b9ab15-5db9-422c-8e80-cf3ae8bf745c"}, "language": "Chinese Simplified", "multiverseId": 147964, "name": "沼泽", "type": "基本地～沼泽", "uuid": "548ef118-6d79-5daa-9006-4d61515d486d"}, {"identifiers": {"multiverseId": "150306", "scryfallId": "05eca292-1fbc-4b5f-8ed3-b283f2e74ea5"}, "language": "French", "multiverseId": 150306, "name": "Marais", "type": "Terrain de base : marais", "uuid": "c4342bad-09df-5c96-82a2-ba71bd1d3333"}, {"identifiers": {"multiverseId": "148731", "scryfallId": "f3c4f59f-b117-4860-ab97-04f74063a3e0"}, "language": "German", "multiverseId": 148731, "name": "Sumpf", "type": "Standardland — Sumpf", "uuid": "0a4498a5-c242-5479-aefc-c8e7b0564d08"}, {"identifiers": {"multiverseId": "149114", "scryfallId": "9752c186-67c7-46b7-a78d-f353580a2feb"}, "language": "Italian", "multiverseId": 149114, "name": "Palude", "type": "Terra Base — Palude", "uuid": "4a1cf309-4d1b-51e0-a747-69c0e378cf7f"}, {"identifiers": {"multiverseId": "148346", "scryfallId": "40bcf612-5da6-4a30-be6f-d3f5b5627200"}, "language": "Japanese", "multiverseId": 148346, "name": "沼", "type": "基本土地 — 沼", "uuid": "84219539-c789-506c-b486-c2c75532e941"}, {"identifiers": {"multiverseId": "149923", "scryfallId": "35e851a3-1e68-4f0e-b65e-ed5880e1b948"}, "language": "Portuguese (Brazil)", "multiverseId": 149923, "name": "Pântano", "type": "Terreno Básico — Pântano", "uuid": "61380d24-5606-5b93-b2a1-61e05a05c0a4"}, {"identifiers": {"multiverseId": "149540", "scryfallId": "156486ef-ff72-4c69-8127-a1870c15051b"}, "language": "Russian", "multiverseId": 149540, "name": "Болото", "type": "Базовая Земля — Болото", "uuid": "d03901c1-f0a4-5730-929b-1a85939b99a1"}, {"identifiers": {"multiverseId": "150689", "scryfallId": "748304a3-a6af-4be4-9ac0-7c013348270b"}, "language": "Spanish", "multiverseId": 150689, "name": "Pantano", "type": "Tierra básica — Pantano", "uuid": "ebfb5176-b5fe-5e83-9527-9ab66ecaf2d5"}], "frameVersion": "2003", "hasFoil": true, "hasNonFoil": true, "identifiers": {"cardKingdomFoilId": "200564", "cardKingdomId": "192571", "cardsphereFoilId": "658", "cardsphereId": "659", "deckboxId": "7514", "mcmId": "16537", "mtgjsonV4Id": "08e90b4f-873f-527a-878e-de1a1f162872", "mtgoFoilId": "27377", "mtgoId": "27376", "multiverseId": "129755", "scryfallCardBackId": "0aeebaf5-8c7d-4636-9e82-8c27447861f7", "scryfallId": "d72aa721-c20c-4306-aca9-dbf2e36d5ba7", "scryfallIllustrationId": "737adc52-899a-4a97-91a5-efa5cf63559b", "scryfallOracleId": "56719f6a-1a6c-4c0a-8d21-18f7d7350b68", "tcgplayerProductId": "15349"}, "isEtched": false, "isFoil": false, "isReprint": true, "language": "English", "layout": "normal", "legalities": {"alchemy": "Legal", "brawl": "Legal", "commander": "Legal", "duel": "Legal", "future": "Legal", "gladiator": "Legal", "historic": "Legal", "legacy": "Legal", "modern": "Legal", "oathbreaker": "Legal", "pauper": "Legal", "paupercommander": "Legal", "penny": "Legal", "pioneer": "Legal", "predh": "Legal", "premodern": "Legal", "standard": "Legal", "standardbrawl": "Legal", "timeless": "Legal", "vintage": "Legal"}, "manaValue": 0.0, "name": "Swamp", "number": "373", "originalText": "B", "printings": ["10E", "2ED", "2XM", "30A", "3ED", "40K", "4BB", "4ED", "5ED", "6ED", "7ED", "8ED", "9ED", "ACR", "AFR", "AKH", "AKR", "ALA", "ANA", "ANB", "ARC", "ATH", "AVR", "BBD", "BFZ", "BLB", "BRB", "BRC", "BRO", "BTD", "C13", "C14", "C15", "C16", "C17", "C18", "C19", "CED", "CEI", "CHK", "CLB", "CLU", "CM2", "CMA", "CMD", "CMM", "CST", "DDC", "DDD", "DDE", "DDH", "DDJ", "DDK", "DDM", "DDN", "DDP", "DDQ", "DDR", "DFT", "DKM", "DMR", "DMU", "DOM", "DPA", "DSK", "DTK", "DVD", "E01", "ELD", "EOE", "FBB", "FDN", "FIC", "FIN", "FRF", "G17", "GK1", "GK2", "GN2", "GN3", "GNT", "GRN", "GVL", "H09", "HBG", "HOP", "HOU", "ICE", "IKO", "INR", "INV", "ISD", "ITP", "J14", "J22", "J25", "JMP", "KHM", "KLD", "KLR", "KTK", "LCI", "LEA", "LEB", "LRW", "LTR", "M10", "M11", "M12", "M13", "M14", "M15", "M19", "M20", "M21", "MBS", "MD1", "ME1", "ME3", "MH2", "MH3", "MID", "MIR", "MKM", "MMQ", "MOM", "MRD", "NEO", "NPH", "ODY", "OLEP", "ONE", "ONS", "ORI", "OTJ", "P02", "P23", "PAL00", "PAL01", "PAL03", "PAL04", "PAL05", "PAL06", "PAL99", "PALP", "PANA", "PARL", "PC2", "PCA", "PD3", "PELP", "PF19", "PF20", "PGPX", "PGRU", "PHUK", "PIP", "PLST", "PMPS", "PMPS06", "PMPS07", "PMPS08", "PMPS09", "PMPS10", "PMPS11", "POR", "PPP1", "PRM", "PRW2", "PRWK", "PS11", "PSAL", "PSS2", "PSS3", "PSS4", "PTC", "PTK", "RAV", "REX", "RIX", "RNA", "ROE", "RQS", "RTR", "S99", "SCD", "SHM", "SIR", "SLD", "SLP", "SNC", "SOI", "SOM", "SPM", "STX", "SUM", "TD0", "TD2", "TDM", "THB", "THS", "TLA", "TMP", "TMT", "TPR", "TSP", "UGL", "UND", "UNF", "UNH", "USG", "UST", "VOW", "WAR", "WC01", "WC02", "WC03", "WC97", "WC98", "WC99", "WHO", "WOE", "XANA", "XLN", "ZEN", "ZNR"], "purchaseUrls": {"cardKingdom": "https://mtgjson.com/links/bb29dc281b7a124d", "cardKingdomFoil": "https://mtgjson.com/links/a04cc532082a199a", "tcgplayer": "https://mtgjson.com/links/48b1e0795040e577"}, "rarity": "common", "setCode": "10E", "sourceProducts": {"foil": ["c5cd29de-5ec9-5e13-b8eb-40e3a9f79f9a", "c690e178-661d-5e17-9b29-a5bf6319a844"], "nonfoil": ["3f1c2aba-e5f1-5ef8-8fd8-f5942fbd5aff", "4831adbb-c0af-5d27-b407-19f2f7805949", "c690e178-661d-5e17-9b29-a5bf6319a844", "ff67afca-f016-5399-83b0-9f9f6e14f950"]}, "subtypes": ["Swamp"], "supertypes": ["Basic"], "text": "({T}: Add {B}.)", "type": "Basic Land — Swamp", "types": ["Land"], "uuid": "4b3673bc-4f31-5877-9710-44d875dcca8a", "variations": ["ec72e59f-bc37-50fd-a1b5-3afac5a402b3", "3e951ede-39fc-58c6-8a89-e2c320902ddd", "eedae11d-cb7c-5b59-bcdd-419e3d6311a1"]}, {"artist": "Jim Nelson", "artistIds": ["aa9f64d1-29e1-4c82-877e-44c18183f40b"], "availability": ["mtgo", "paper"], "boosterTypes": ["default"], "borderColor": "black", "colorIdentity": ["B"], "colors": [], "convertedManaCost": 0.0, "count": 3, "edhrecSaltiness": 0.33, "finishes": ["nonfoil", "foil"], "foreignData": [{"identifiers": {"multiverseId": "147962", "scryfallId": "0ca942dc-e88f-423a-b113-a535115be873"}, "language": "Chinese Simplified", "multiverseId": 147962, "name": "沼泽", "type": "基本地～沼泽", "uuid": "fe617a2d-b52a-5916-b4f5-b5b11aa79d0e"}, {"identifiers": {"multiverseId": "150307", "scryfallId": "4f321f1b-db55-40f3-8e4d-538eb82d0bb5"}, "language": "French", "multiverseId": 150307, "name": "Marais", "type": "Terrain de base : marais", "uuid": "381ba4a0-1f28-541f-8405-e16aab2838fb"}, {"identifiers": {"multiverseId": "148728", "scryfallId": "47dc0906-50c3-4455-8472-b31c5932ff42"}, "language": "German", "multiverseId": 148728, "name": "Sumpf", "type": "Standardland — Sumpf", "uuid": "b4b82c16-1488-51c3-a392-39e0fe85e00f"}, {"identifiers": {"multiverseId": "149111", "scryfallId": "6abba96e-168e-42b3-97fc-e967f668c7cf"}, "language": "Italian", "multiverseId": 149111, "name": "Palude", "type": "Terra Base — Palude", "uuid": "a613960e-32a0-5e1d-9ec5-436efa1b811b"}, {"identifiers": {"multiverseId": "149924", "scryfallId": "5337396f-60c0-49d7-b894-8018c775f2de"}, "language": "Portuguese (Brazil)", "multiverseId": 149924, "name": "Pântano", "type": "Terreno Básico — Pântano", "uuid": "a1bf9e69-4a5b-51b0-8897-e61f356cc645"}, {"identifiers": {"multiverseId": "149541", "scryfallId": "971265f3-96d3-4ba9-b4b6-b2a81edc063f"}, "language": "Russian", "multiverseId": 149541, "name": "Болото", "type": "Базовая Земля — Болото", "uuid": "ba2d6ad7-d9b3-5f1e-9f5d-529631a2528e"}, {"identifiers": {"multiverseId": "150690", "scryfallId": "1041ea6b-4a26-4f53-808f-089a977f35bb"}, "language": "Spanish", "multiverseId": 150690, "name": "Pantano", "type": "Tierra básica — Pantano", "uuid": "14e2ec1c-6680-5bff-8382-6dbec6926c31"}], "frameVersion": "2003", "hasFoil": true, "hasNonFoil": true, "identifiers": {"cardKingdomFoilId": "200565", "cardKingdomId": "192572", "cardsphereFoilId": "660", "cardsphereId": "661", "deckboxId": "7513", "mcmId": "16538", "mtgjsonV4Id": "961be428-e000-5a5e-a578-cf8ba3634c44", "mtgoFoilId": "27650", "mtgoId": "27649", "multiverseId": "129756", "scryfallCardBackId": "0aeebaf5-8c7d-4636-9e82-8c27447861f7", "scryfallId": "9eaedaf2-a9a3-44c6-84c1-4cc2da1da459", "scryfallIllustrationId": "395a8d71-37ee-4876-8b44-0970ad3a56c8", "scryfallOracleId": "56719f6a-1a6c-4c0a-8d21-18f7d7350b68", "tcgplayerProductId": "15350"}, "isEtched": false, "isFoil": false, "isReprint": true, "language": "English", "layout": "normal", "legalities": {"alchemy": "Legal", "brawl": "Legal", "commander": "Legal", "duel": "Legal", "future": "Legal", "gladiator": "Legal", "historic": "Legal", "legacy": "Legal", "modern": "Legal", "oathbreaker": "Legal", "pauper": "Legal", "paupercommander": "Legal", "penny": "Legal", "pioneer": "Legal", "predh": "Legal", "premodern": "Legal", "standard": "Legal", "standardbrawl": "Legal", "timeless": "Legal", "vintage": "Legal"}, "manaValue": 0.0, "name": "Swamp", "number": "374", "originalText": "B", "printings": ["10E", "2ED", "2XM", "30A", "3ED", "40K", "4BB", "4ED", "5ED", "6ED", "7ED", "8ED", "9ED", "ACR", "AFR", "AKH", "AKR", "ALA", "ANA", "ANB", "ARC", "ATH", "AVR", "BBD", "BFZ", "BLB", "BRB", "BRC", "BRO", "BTD", "C13", "C14", "C15", "C16", "C17", "C18", "C19", "CED", "CEI", "CHK", "CLB", "CLU", "CM2", "CMA", "CMD", "CMM", "CST", "DDC", "DDD", "DDE", "DDH", "DDJ", "DDK", "DDM", "DDN", "DDP", "DDQ", "DDR", "DFT", "DKM", "DMR", "DMU", "DOM", "DPA", "DSK", "DTK", "DVD", "E01", "ELD", "EOE", "FBB", "FDN", "FIC", "FIN", "FRF", "G17", "GK1", "GK2", "GN2", "GN3", "GNT", "GRN", "GVL", "H09", "HBG", "HOP", "HOU", "ICE", "IKO", "INR", "INV", "ISD", "ITP", "J14", "J22", "J25", "JMP", "KHM", "KLD", "KLR", "KTK", "LCI", "LEA", "LEB", "LRW", "LTR", "M10", "M11", "M12", "M13", "M14", "M15", "M19", "M20", "M21", "MBS", "MD1", "ME1", "ME3", "MH2", "MH3", "MID", "MIR", "MKM", "MMQ", "MOM", "MRD", "NEO", "NPH", "ODY", "OLEP", "ONE", "ONS", "ORI", "OTJ", "P02", "P23", "PAL00", "PAL01", "PAL03", "PAL04", "PAL05", "PAL06", "PAL99", "PALP", "PANA", "PARL", "PC2", "PCA", "PD3", "PELP", "PF19", "PF20", "PGPX", "PGRU", "PHUK", "PIP", "PLST", "PMPS", "PMPS06", "PMPS07", "PMPS08", "PMPS09", "PMPS10", "PMPS11", "POR", "PPP1", "PRM", "PRW2", "PRWK", "PS11", "PSAL", "PSS2", "PSS3", "PSS4", "PTC", "PTK", "RAV", "REX", "RIX", "RNA", "ROE", "RQS", "RTR", "S99", "SCD", "SHM", "SIR", "SLD", "SLP", "SNC", "SOI", "SOM", "SPM", "STX", "SUM", "TD0", "TD2", "TDM", "THB", "THS", "TLA", "TMP", "TMT", "TPR", "TSP", "UGL", "UND", "UNF", "UNH", "USG", "UST", "VOW", "WAR", "WC01", "WC02", "WC03", "WC97", "WC98", "WC99", "WHO", "WOE", "XANA", "XLN", "ZEN", "ZNR"], "purchaseUrls": {"cardKingdom": "https://mtgjson.com/links/ee9eb3ee51d42001", "cardKingdomFoil": "https://mtgjson.com/links/b0a3df5f049e33e7", "tcgplayer": "https://mtgjson.com/links/fdbb23462a2952ae"}, "rarity": "common", "setCode": "10E", "sourceProducts": {"foil": ["c5cd29de-5ec9-5e13-b8eb-40e3a9f79f9a", "c690e178-661d-5e17-9b29-a5bf6319a844"], "nonfoil": ["3f1c2aba-e5f1-5ef8-8fd8-f5942fbd5aff", "4831adbb-c0af-5d27-b407-19f2f7805949", "c690e178-661d-5e17-9b29-a5bf6319a844", "ff67afca-f016-5399-83b0-9f9f6e14f950"]}, "subtypes": ["Swamp"], "supertypes": ["Basic"], "text": "({T}: Add {B}.)", "type": "Basic Land — Swamp", "types": ["Land"], "uuid": "3e951ede-39fc-58c6-8a89-e2c320902ddd", "variations": ["ec72e59f-bc37-50fd-a1b5-3afac5a402b3", "4b3673bc-4f31-5877-9710-44d875dcca8a", "eedae11d-cb7c-5b59-bcdd-419e3d6311a1"]}, {"artist": "Richard Wright", "artistIds": ["7b1b0ce9-2c58-4321-a2a7-cdc94feae082"], "availability": ["mtgo", "paper"], "boosterTypes": ["default"], "borderColor": "black", "colorIdentity": ["B"], "colors": [], "convertedManaCost": 0.0, "count": 3, "edhrecSaltiness": 0.33, "finishes": ["nonfoil", "foil"], "foreignData": [{"identifiers": {"multiverseId": "150308", "scryfallId": "4151dff2-7374-414a-945e-dcf1aaf0328e"}, "language": "French", "multiverseId": 150308, "name": "Marais", "type": "Terrain de base : marais", "uuid": "78b40f85-b683-59de-aea5-8b87136b0084"}, {"identifiers": {"multiverseId": "148729", "scryfallId": "d165847e-e3ba-4d64-82bc-88199bfa0af7"}, "language": "German", "multiverseId": 148729, "name": "Sumpf", "type": "Standardland - Sumpf", "uuid": "1589cc98-b1c8-58a2-81a4-c00953d6e21d"}, {"identifiers": {"multiverseId": "149112", "scryfallId": "469c8eec-ecbc-4bbd-beba-a2d26b5b9a0c"}, "language": "Italian", "multiverseId": 149112, "name": "Palude", "type": "Terra Base - Palude", "uuid": "6e9c5e19-145a-5d72-90f9-4e02b6d7d475"}, {"identifiers": {"multiverseId": "148348", "scryfallId": "32aec396-f28b-40ba-ab88-0f959a05b64d"}, "language": "Japanese", "multiverseId": 148348, "name": "沼", "type": "基本土地 — 沼", "uuid": "8bb35bdc-a3c1-5701-8951-a95ad1340c6f"}], "frameVersion": "2003", "hasFoil": true, "hasNonFoil": true, "identifiers": {"cardKingdomFoilId": "200566", "cardKingdomId": "192573", "cardsphereFoilId": "662", "cardsphereId": "663", "deckboxId": "7511", "mcmId": "16539", "mtgjsonV4Id": "171539f5-8ed4-5f88-a050-51890e7c5529", "mtgoFoilId": "27732", "mtgoId": "27731", "multiverseId": "129757", "scryfallCardBackId": "0aeebaf5-8c7d-4636-9e82-8c27447861f7", "scryfallId": "0eed3360-1634-4e60-b24d-4128c4896994", "scryfallIllustrationId": "f52de449-38ef-4a05-87de-c433b315982d", "scryfallOracleId": "56719f6a-1a6c-4c0a-8d21-18f7d7350b68", "tcgplayerProductId": "15351"}, "isEtched": false, "isFoil": false, "isReprint": true, "language": "English", "layout": "normal", "legalities": {"alchemy": "Legal", "brawl": "Legal", "commander": "Legal", "duel": "Legal", "future": "Legal", "gladiator": "Legal", "historic": "Legal", "legacy": "Legal", "modern": "Legal", "oathbreaker": "Legal", "pauper": "Legal", "paupercommander": "Legal", "penny": "Legal", "pioneer": "Legal", "predh": "Legal", "premodern": "Legal", "standard": "Legal", "standardbrawl": "Legal", "timeless": "Legal", "vintage": "Legal"}, "manaValue": 0.0, "name": "Swamp", "number": "375", "originalText": "B", "printings": ["10E", "2ED", "2XM", "30A", "3ED", "40K", "4BB", "4ED", "5ED", "6ED", "7ED", "8ED", "9ED", "ACR", "AFR", "AKH", "AKR", "ALA", "ANA", "ANB", "ARC", "ATH", "AVR", "BBD", "BFZ", "BLB", "BRB", "BRC", "BRO", "BTD", "C13", "C14", "C15", "C16", "C17", "C18", "C19", "CED", "CEI", "CHK", "CLB", "CLU", "CM2", "CMA", "CMD", "CMM", "CST", "DDC", "DDD", "DDE", "DDH", "DDJ", "DDK", "DDM", "DDN", "DDP", "DDQ", "DDR", "DFT", "DKM", "DMR", "DMU", "DOM", "DPA", "DSK", "DTK", "DVD", "E01", "ELD", "EOE", "FBB", "FDN", "FIC", "FIN", "FRF", "G17", "GK1", "GK2", "GN2", "GN3", "GNT", "GRN", "GVL", "H09", "HBG", "HOP", "HOU", "ICE", "IKO", "INR", "INV", "ISD", "ITP", "J14", "J22", "J25", "JMP", "KHM", "KLD", "KLR", "KTK", "LCI", "LEA", "LEB", "LRW", "LTR", "M10", "M11", "M12", "M13", "M14", "M15", "M19", "M20", "M21", "MBS", "MD1", "ME1", "ME3", "MH2", "MH3", "MID", "MIR", "MKM", "MMQ", "MOM", "MRD", "NEO", "NPH", "ODY", "OLEP", "ONE", "ONS", "ORI", "OTJ", "P02", "P23", "PAL00", "PAL01", "PAL03", "PAL04", "PAL05", "PAL06", "PAL99", "PALP", "PANA", "PARL", "PC2", "PCA", "PD3", "PELP", "PF19", "PF20", "PGPX", "PGRU", "PHUK", "PIP", "PLST", "PMPS", "PMPS06", "PMPS07", "PMPS08", "PMPS09", "PMPS10", "PMPS11", "POR", "PPP1", "PRM", "PRW2", "PRWK", "PS11", "PSAL", "PSS2", "PSS3", "PSS4", "PTC", "PTK", "RAV", "REX", "RIX", "RNA", "ROE", "RQS", "RTR", "S99", "SCD", "SHM", "SIR", "SLD", "SLP", "SNC", "SOI", "SOM", "SPM", "STX", "SUM", "TD0", "TD2", "TDM", "THB", "THS", "TLA", "TMP", "TMT", "TPR", "TSP", "UGL", "UND", "UNF", "UNH", "USG", "UST", "VOW", "WAR", "WC01", "WC02", "WC03", "WC97", "WC98", "WC99", "WHO", "WOE", "XANA", "XLN", "ZEN", "ZNR"], "purchaseUrls": {"cardKingdom": "https://mtgjson.com/links/c128cd3fbaf64ffc", "cardKingdomFoil": "https://mtgjson.com/links/9227bd518ccef200", "tcgplayer": "https://mtgjson.com/links/6b67ea5e3cc7a08a"}, "rarity": "common", "setCode": "10E", "sourceProducts": {"foil": ["c5cd29de-5ec9-5e13-b8eb-40e3a9f79f9a", "c690e178-661d-5e17-9b29-a5bf6319a844"], "nonfoil": ["3f1c2aba-e5f1-5ef8-8fd8-f5942fbd5aff", "4831adbb-c0af-5d27-b407-19f2f7805949", "c690e178-661d-5e17-9b29-a5bf6319a844", "ff67afca-f016-5399-83b0-9f9f6e14f950"]}, "subtypes": ["Swamp"], "supertypes": ["Basic"], "text": "({T}: Add {B}.)", "type": "Basic Land — Swamp", "types": ["Land"], "uuid": "eedae11d-cb7c-5b59-bcdd-419e3d6311a1", "variations": ["ec72e59f-bc37-50fd-a1b5-3afac5a402b3", "4b3673bc-4f31-5877-9710-44d875dcca8a", "3e951ede-39fc-58c6-8a89-e2c320902ddd"]}, {"artist": "Kev Walker", "artistIds": ["f366a0ee-a0cd-466d-ba6a-90058c7a31a6"], "availability": ["mtgo", "paper"], "boosterTypes": ["default"], "borderColor": "black", "colorIdentity": ["B"], "colors": ["B"], "convertedManaCost": 4.0, "count": 2, "edhrecRank": 25582, "edhrecSaltiness": 0.69, "finishes": ["nonfoil", "foil"], "flavorText": "\"Tonight, madam, it's your money *and* your life.\"", "foreignData": [{"flavorText": "「夫人，今晚留下妳的钱，还有妳的命。」", "identifiers": {"multiverseId": "147774", "scryfallId": "e3b1d290-6a17-490c-91eb-21ddc80c641e"}, "language": "Chinese Simplified", "multiverseId": 147774, "name": "大道抢匪", "text": "当大道抢匪进场时，你获得2点生命且目标对手失去2点生命。", "type": "生物～人类／佣兵", "uuid": "635b11f6-218b-551e-b02d-d0fe086bceb4"}, {"flavorText": "« Ce soir, madame, c'est la bourse et la vie. »", "identifiers": {"multiverseId": "150083", "scryfallId": "66e91f33-7cb9-4001-b304-75573cfd9544"}, "language": "French", "multiverseId": 150083, "name": "Bandit de grand chemin", "text": "Quand le Bandit de grand chemin arrive en jeu, vous gagnez 2 points de vie et l'adversaire ciblé perd 2 points de vie.", "type": "Créature : humain et mercenaire", "uuid": "5334d6f2-16b2-569f-a0bb-5d45400b7d27"}, {"flavorText": "„Heute nacht, Madame, ist es Geld und Leben.\"", "identifiers": {"multiverseId": "148540", "scryfallId": "145f7743-f73b-49b3-8a5b-a8d28f399941"}, "language": "German", "multiverseId": 148540, "name": "Straßenräuber", "text": "Wenn der Straßenräuber ins Spiel kommt, erhältst du 2 Lebenspunkte dazu, und ein Gegner deiner Wahl verliert 2 Lebenspunkte.", "type": "Kreatur — Mensch, Söldner", "uuid": "e60d76bc-4e08-5b3c-a929-73583666adb6"}, {"flavorText": "\"Stanotte, mia signora, prenderò i tuoi soldi e la tua vita.\"", "identifiers": {"multiverseId": "148923", "scryfallId": "b3138fd9-cb65-4e20-99a9-b3463f73406e"}, "language": "Italian", "multiverseId": 148923, "name": "Rapinatore di Strada", "text": "Quando il Rapinatore di Strada entra in gioco, guadagni 2 punti vita e un avversario bersaglio perde 2 punti vita.", "type": "Creatura — Mercenario Umano", "uuid": "a38132eb-facc-5ba8-a4b3-b95a18a5fa4a"}, {"flavorText": "今夜はお金をいただきますよ、奥様。それから、お命もね。", "identifiers": {"multiverseId": "148157", "scryfallId": "3f98348d-1b50-4542-a9d1-4cc22c84f517"}, "language": "Japanese", "multiverseId": 148157, "name": "街道筋の強盗", "text": "街道筋の強盗が場に出たとき、対戦相手１人を対象とする。あなたは２点のライフを得て、そのプレイヤーは２点のライフを失う。", "type": "クリーチャー — 人間・傭兵", "uuid": "9cff42d5-648a-52fc-a6e0-ae71569b99dc"}, {"flavorText": "\"Hoje à noite, madame, é o seu dinheiro e a sua vida.\"", "identifiers": {"multiverseId": "149700", "scryfallId": "aef84b6b-a077-4d07-a001-5f75d98d45ac"}, "language": "Portuguese (Brazil)", "multiverseId": 149700, "name": "Saltimbancos", "text": "Quando Saltimbancos entra em jogo, você ganha 2 pontos de vida e o oponente alvo perde 2 pontos de vida.", "type": "Criatura — Humano Mercenário", "uuid": "410ec667-4b0f-5ea0-8b37-34084ca598e9"}, {"flavorText": "\"Мадам, кошелек или жизнь, а лучше и то и другое\".", "identifiers": {"multiverseId": "149317", "scryfallId": "195cdcf8-3e51-454b-94d2-a4c09d0cad52"}, "language": "Russian", "multiverseId": 149317, "name": "Бандит с Большой Дороги", "text": "Когда Бандит с Большой Дороги входит в игру, вы получаете 2 жизни, а целевой оппонент теряет 2 жизни.", "type": "Существо — Человек Наемник", "uuid": "be95d1d9-19fe-5526-aa5e-a6cc6c778ec7"}, {"flavorText": "\"Esta noche, señora, es su dinero y su vida.\"", "identifiers": {"multiverseId": "150466", "scryfallId": "d2e907e2-24f8-4beb-801f-7459f2598136"}, "language": "Spanish", "multiverseId": 150466, "name": "Asaltante de la carretera", "text": "Cuando el Asaltante de la carretera entre en juego, ganas 2 vidas y el oponente objetivo pierde 2 vidas.", "type": "Criatura — Mercenario humano", "uuid": "31ca7f44-5153-5af4-808f-e7e187909e1f"}], "frameVersion": "2003", "hasFoil": true, "hasNonFoil": true, "identifiers": {"cardKingdomFoilId": "123236", "cardKingdomId": "122868", "cardsphereFoilId": "279", "cardsphereId": "280", "deckboxId": "1867", "mcmId": "16314", "mcmMetaId": "2695", "mtgjsonV4Id": "66d5552b-9be2-5080-87c8-ddbd6ac8021c", "mtgoFoilId": "27323", "mtgoId": "27322", "multiverseId": "129564", "scryfallCardBackId": "0aeebaf5-8c7d-4636-9e82-8c27447861f7", "scryfallId": "b9d4d095-664e-4704-b922-f868d0d454d3", "scryfallIllustrationId": "28a29c26-47e1-470d-af51-0ba7929f68c7", "scryfallOracleId": "5de0769e-5141-42d5-aaa6-549cfc154de8", "tcgplayerProductId": "15161"}, "isEtched": false, "isFoil": false, "isReprint": true, "language": "English", "layout": "normal", "legalities": {"commander": "Legal", "duel": "Legal", "legacy": "Legal", "modern": "Legal", "oathbreaker": "Legal", "pauper": "Legal", "paupercommander": "Legal", "penny": "Legal", "predh": "Legal", "premodern": "Legal", "vintage": "Legal"}, "manaCost": "{2}{B}{B}", "manaValue": 4.0, "name": "Highway Robber", "number": "150", "originalText": "When Highway Robber comes into play, you gain 2 life and target opponent loses 2 life.", "power": "2", "printings": ["10E", "9ED", "DDM", "MMQ"], "purchaseUrls": {"cardKingdom": "https://mtgjson.com/links/0db59393e198d3a3", "cardKingdomFoil": "https://mtgjson.com/links/afb7bcfeca148ee5", "cardmarket": "https://mtgjson.com/links/844c62fbc032f7da", "tcgplayer": "https://mtgjson.com/links/725153474110c22a"}, "rarity": "common", "setCode": "10E", "sourceProducts": {"foil": ["c5cd29de-5ec9-5e13-b8eb-40e3a9f79f9a", "c690e178-661d-5e17-9b29-a5bf6319a844"], "nonfoil": ["3f1c2aba-e5f1-5ef8-8fd8-f5942fbd5aff", "4831adbb-c0af-5d27-b407-19f2f7805949", "c690e178-661d-5e17-9b29-a5bf6319a844"]}, "subtypes": ["Human", "Mercenary"], "supertypes": [], "text": "When this creature enters, target opponent loses 2 life and you gain 2 life.", "toughness": "2", "type": "Creature — Human Mercenary", "types": ["Creature"], "uuid": "f58e52e4-ab1c-5ccf-a751-5d174e5138a2"}, {"artist": "William O'Connor", "artistIds": ["4f1c2854-d7a8-4f9a-8b3d-72a16eb7bdc1"], "availability": ["mtgo", "paper"], "boosterTypes": ["default"], "borderColor": "black", "colorIdentity": ["B"], "colors": ["B"], "convertedManaCost": 4.0, "count": 2, "edhrecRank": 26348, "edhrecSaltiness": 0.29, "finishes": ["nonfoil", "foil"], "flavorText": "Winnowers live to eliminate eyeblights, creatures the elves deem too ugly to exist.", "foreignData": [{"flavorText": "筛除者与生俱来的使命就是消灭碍眼；那是地精判定为丑陋得不该存在之物。", "identifiers": {"multiverseId": "154923", "scryfallId": "34ae7a25-721b-497b-8b32-d3cca2b122d2"}, "language": "Chinese Simplified", "multiverseId": 154923, "name": "月地黄筛除者", "text": "死触 （每当此生物对任一生物造成伤害时，消灭后者。）", "type": "生物～地精／浪客", "uuid": "89b7e36b-ea4f-5d42-a654-48441d74a612"}, {"flavorText": "La fonction des vanneurs est d'éliminer les dysmèles, les créatures que les elfes estiment trop laides pour exister.", "identifiers": {"multiverseId": "155535", "scryfallId": "8490b7f3-f99f-4a09-8433-eff67c5c21bf"}, "language": "French", "multiverseId": 155535, "name": "Vanneur à la digitale lunaire", "text": "Contact mortel (À chaque fois que cette créature inflige des blessures à une créature, détruisez la créature blessée.)", "type": "Créature : elfe et gredin", "uuid": "7090218a-4c41-51a8-998c-907989079df9"}, {"flavorText": "Ausdünner leben, um Augenweh zu eliminieren — so nennen Elfen die Kreaturen, die sie für zu hässlich halten, um überleben zu dürfen.", "identifiers": {"multiverseId": "154622", "scryfallId": "090debd4-e66c-495c-8f57-0f144d7eacae"}, "language": "German", "multiverseId": 154622, "name": "Mondfingerhut-Ausdünner", "text": "Todesberührung (Immer wenn diese Kreatur einer Kreatur Schaden zufügt, zerstöre jene Kreatur.)", "type": "Kreatur — Elf, Räuber", "uuid": "ebac6864-3845-5fcd-9f97-f01d2b237133"}, {"flavorText": "I setacciatori vivono per eliminare i mal'occhi, creature che gli elfi ritengono troppo brutte per esistere.", "identifiers": {"multiverseId": "155836", "scryfallId": "72031e6f-3438-4537-a235-23ec0aeea543"}, "language": "Italian", "multiverseId": 155836, "name": "Setacciatore di Digitale Selenica", "text": "Tocco letale (Ogniqualvolta questa creatura infligge danno a una creatura, distruggi quella creatura.)", "type": "Creatura — Farabutto Elfo", "uuid": "15490778-3c59-5e93-934e-0cd49fb01a72"}, {"flavorText": "醜すぎて存在を認めるわけにいかないとエルフたちが判断した眼腐りを廃除するため、選別者は生きている。", "identifiers": {"multiverseId": "156137", "scryfallId": "bdc1ea54-4cac-41f6-9a29-ea789da3f17a"}, "language": "Japanese", "multiverseId": 156137, "name": "ツキノテブクロの選別者", "text": "接死 （このクリーチャーがいずれかのクリーチャーにダメージを与えるたび、そのクリーチャーを破壊する。）", "type": "クリーチャー — エルフ・ならず者", "uuid": "8ee8bb0c-64ae-539c-b580-33d643d54bae"}, {"flavorText": "Os peneiradores vivem para eliminar os seca-olhos, criaturas que os elfos julgam feias demais para existir.", "identifiers": {"multiverseId": "157040", "scryfallId": "23b06e22-9061-4ffc-9dc0-b288bf314515"}, "language": "Portuguese (Brazil)", "multiverseId": 157040, "name": "Peneirador Luvalua", "text": "Toque mortífero (Toda vez que esta criatura causar dano a outra criatura, destrua aquela criatura.)", "type": "Criatura — Ladino Elfo", "uuid": "5862d68d-f1ab-5535-824b-fa7815d65f8e"}, {"flavorText": "Смысл жизни отсеивателей состоит в уничтожении \"порчеглазов\" существ, которые, согласно эльфам, не имеют права на существование из-за своей уродливости.", "identifiers": {"multiverseId": "156438", "scryfallId": "00fd380b-c6c0-4ae3-aa83-ed89e0e5b129"}, "language": "Russian", "multiverseId": 156438, "name": "Отсеиватель с Луноцветом", "text": "Смертельное касание (Каждый раз, когда это существо наносит повреждения другому существу, уничтожьте то существо.)", "type": "Существо — Эльф Бродяга", "uuid": "e19aa45e-6ff4-5317-91ed-2b15feb7c60f"}, {"flavorText": "Los aventadores viven para eliminar a las desgracias visuales, criaturas que los elfos deciden son demasiado feas como para existir.", "identifiers": {"multiverseId": "156739", "scryfallId": "d48d17b1-fedb-41ee-855a-0e612ff5cc44"}, "language": "Spanish", "multiverseId": 156739, "name": "Aventador de selenera", "text": "Toque mortal. (Siempre que esta criatura haga daño a una criatura, destruye esa criatura.)", "type": "Criatura — Bribón elfo", "uuid": "8b309136-1a66-5423-bf2c-51f87db8c9be"}], "frameVersion": "2003", "hasFoil": true, "hasNonFoil": true, "identifiers": {"cardKingdomFoilId": "123826", "cardKingdomId": "123627", "cardsphereFoilId": "25477", "cardsphereId": "25478", "deckboxId": "3352", "mcmId": "17867", "mcmMetaId": "9238", "mtgjsonV4Id": "c63c3695-9272-5d07-bf61-a34c03eb556b", "mtgoFoilId": "28306", "mtgoId": "28305", "multiverseId": "139483", "scryfallCardBackId": "0aeebaf5-8c7d-4636-9e82-8c27447861f7", "scryfallId": "effb7761-98a8-4cb8-883a-ddcb91d30c08", "scryfallIllustrationId": "fa00b20c-82dc-4705-a5ce-99c7a00b1361", "scryfallOracleId": "d4870995-f434-4985-a921-1dc9556cee41", "tcgplayerProductId": "15576"}, "isEtched": false, "isFoil": false, "keywords": ["Deathtouch"], "language": "English", "layout": "normal", "legalities": {"commander": "Legal", "duel": "Legal", "legacy": "Legal", "modern": "Legal", "oathbreaker": "Legal", "pauper": "Legal", "paupercommander": "Legal", "penny": "Legal", "predh": "Legal", "vintage": "Legal"}, "manaCost": "{3}{B}", "manaValue": 4.0, "name": "Moonglove Winnower", "number": "126", "originalText": "Deathtouch (Whenever this creature deals damage to a creature, destroy that creature.)", "power": "2", "printings": ["DPA", "LRW", "PS11"], "purchaseUrls": {"cardKingdom": "https://mtgjson.com/links/4de93f09df1ed2f4", "cardKingdomFoil": "https://mtgjson.com/links/bcc816ad7420559b", "cardmarket": "https://mtgjson.com/links/4ec04c55ed503afb", "tcgplayer": "https://mtgjson.com/links/fefdc1977af96981"}, "rarity": "common", "setCode": "LRW", "sourceProducts": {"foil": ["17d7dd33-f196-53f9-aa62-f12b5a5a32b4", "8e0fd374-3d5a-509d-b778-919c9cbec9f1"], "nonfoil": ["0878061e-0b9e-5b03-babe-4ca5364b0ad5", "17d7dd33-f196-53f9-aa62-f12b5a5a32b4", "220a5e02-5213-5d46-a9d1-d322b74f05a6", "3f1c2aba-e5f1-5ef8-8fd8-f5942fbd5aff", "e6b1e5bf-a329-54f7-ac5e-8fe8898458ae"]}, "subtypes": ["Elf", "Rogue"], "supertypes": [], "text": "Deathtouch (Any amount of damage this deals to a creature is enough to destroy it.)", "toughness": "3", "type": "Creature — Elf Rogue", "types": ["Creature"], "uuid": "4084fa60-05ee-5a72-97d7-a163fc4a3848"}, {"artist": "Carl Critchlow", "artistIds": ["17948f16-611a-44b8-8d10-9895a0bdfff1"], "availability": ["mtgo", "paper"], "boosterTypes": ["default"], "borderColor": "black", "colorIdentity": ["B"], "colors": ["B"], "convertedManaCost": 2.0, "count": 2, "edhrecRank": 10880, "edhrecSaltiness": 0.37, "finishes": ["nonfoil", "foil"], "flavorText": "Nothing is sacred to rats. Everything is simply another meal.", "foreignData": [{"flavorText": "老鼠的眼中没有神圣之物， 所有东西都是一顿饱餐。", "identifiers": {"multiverseId": "147883", "scryfallId": "2631267a-5690-46c1-9c15-0c44b3372932"}, "language": "Chinese Simplified", "multiverseId": 147883, "name": "贪吃老鼠", "text": "当贪吃老鼠进场时，目标对手弃一张牌。", "type": "生物～老鼠", "uuid": "26bf29e8-6048-5ac1-846e-688c6cd3d050"}, {"flavorText": "Pour les rats, rien n'est sacré. La vie n'est qu'un continuel repas.", "identifiers": {"multiverseId": "150104", "scryfallId": "9713a996-1508-448d-bf6d-a16fd06d076c"}, "language": "French", "multiverseId": 150104, "name": "Rats voraces", "text": "Quand ces Rats voraces arrivent en jeu, l'adversaire ciblé se défausse d'une carte.", "type": "Créature : rat", "uuid": "a41a13b9-6b8c-579f-961a-a67e3c9d6507"}, {"flavorText": "Den Ratten ist nichts heilig. Alles ist nur eine weitere Mahlzeit.", "identifiers": {"multiverseId": "148649", "scryfallId": "35a5bc91-d239-41f3-a764-1b45c8039b5d"}, "language": "German", "multiverseId": 148649, "name": "Gierige Ratten", "text": "Wenn die Gierigen Ratten ins Spiel kommen, wirft ein Gegner deiner Wahl eine Karte aus seiner Hand ab.", "type": "Kreatur — Ratte", "uuid": "1a6f783f-9308-54ba-8309-36153acc5d4c"}, {"flavorText": "Niente è sacro per i ratti: tutte le cose sono considerate alla stregua di un pasto.", "identifiers": {"multiverseId": "149032", "scryfallId": "74f2432f-90dc-4380-9ca4-b9471e5799ab"}, "language": "Italian", "multiverseId": 149032, "name": "Ratti Famelici", "text": "Quando i Ratti Famelici entrano in gioco, un avversario bersaglio scarta una carta.", "type": "Creatura — Ratto", "uuid": "f1237f0c-15c0-5b60-956f-d77836653a87"}, {"flavorText": "このネズミらにとって敬意を表すべきものなんか何もない。 何を見てもエサだと思うんだから。", "identifiers": {"multiverseId": "148266", "scryfallId": "69529ea3-f777-4bd7-bcda-1183a31c790a"}, "language": "Japanese", "multiverseId": 148266, "name": "貪欲なるネズミ", "text": "貪欲なるネズミが場に出たとき、対戦相手１人を対象とする。そのプレイヤーはカードを１枚捨てる。", "type": "クリーチャー — ネズミ", "uuid": "03932450-d02b-51c6-badd-2e1582e529cc"}, {"flavorText": "Nada é sagrado para os ratos. Tudo é apenas mais uma refeição.", "identifiers": {"multiverseId": "149721", "scryfallId": "eeaf19a8-d165-4481-8d39-1b4a02777626"}, "language": "Portuguese (Brazil)", "multiverseId": 149721, "name": "Ratos Vorazes", "text": "Quando Ratos Vorazes entra em jogo, o oponente alvo descarta um card.", "type": "Criatura — Rato", "uuid": "cc7001d1-8c6c-56ae-a2fe-d8b7eb7bd88c"}, {"flavorText": "Для крыс нет ничего святого. Для них весь мир еда.", "identifiers": {"multiverseId": "149338", "scryfallId": "bd3097fb-25f9-44ed-a2e6-25fe36e5ae8d"}, "language": "Russian", "multiverseId": 149338, "name": "Прожорливые Крысы", "text": "Когда Прожорливые Крысы входят в игру, целевой оппонент сбрасывает карту.", "type": "Существо — Крыса", "uuid": "f43535d8-0995-552c-a16a-020767f41412"}, {"flavorText": "Nada es sagrado para las ratas. Todo es simplemente otra comida.", "identifiers": {"multiverseId": "150487", "scryfallId": "47cf3b58-74fb-4c91-aa2d-f5da63509e11"}, "language": "Spanish", "multiverseId": 150487, "name": "Ratas rapaces", "text": "Cuando las Ratas rapaces entren en juego, el oponente objetivo descarta una carta.", "type": "Criatura — Rata", "uuid": "cdb16216-8c4d-5387-97f6-35a74de71f65"}], "frameVersion": "2003", "hasFoil": true, "hasNonFoil": true, "identifiers": {"cardKingdomFoilId": "123257", "cardKingdomId": "122889", "cardsphereFoilId": "496", "cardsphereId": "497", "deckboxId": "2189", "mcmId": "16335", "mcmMetaId": "4530", "mtgjsonV4Id": "f80d865b-a718-551e-a5ee-046647592b59", "mtgoFoilId": "27309", "mtgoId": "27308", "multiverseId": "129692", "scryfallCardBackId": "0aeebaf5-8c7d-4636-9e82-8c27447861f7", "scryfallId": "03a8b556-6e18-46ee-80f8-cbd922e37432", "scryfallIllustrationId": "fba238bb-ed71-4d11-b78d-04d1e57e8a0a", "scryfallOracleId": "2fa1bbfd-92b5-482c-b32d-4cdc286474c4", "tcgplayerProductId": "15269"}, "isEtched": false, "isFoil": false, "isReprint": true, "language": "English", "layout": "normal", "legalities": {"commander": "Legal", "duel": "Legal", "legacy": "Legal", "modern": "Legal", "oathbreaker": "Legal", "pauper": "Legal", "paupercommander": "Legal", "penny": "Legal", "predh": "Legal", "premodern": "Legal", "vintage": "Legal"}, "manaCost": "{1}{B}", "manaValue": 2.0, "name": "Ravenous Rats", "number": "171", "originalText": "When Ravenous Rats comes into play, target opponent discards a card.", "power": "1", "printings": ["10E", "8ED", "9ED", "DDD", "DDJ", "DPA", "GVL", "INV", "M13", "P02", "PS11", "S99", "UDS", "WC99"], "purchaseUrls": {"cardKingdom": "https://mtgjson.com/links/e2de939e20f84abd", "cardKingdomFoil": "https://mtgjson.com/links/2814a085446916b9", "cardmarket": "https://mtgjson.com/links/5308f8ae898c5258", "tcgplayer": "https://mtgjson.com/links/fc0fb8f521d488b5"}, "rarity": "common", "setCode": "10E", "sourceProducts": {"foil": ["c5cd29de-5ec9-5e13-b8eb-40e3a9f79f9a", "c690e178-661d-5e17-9b29-a5bf6319a844"], "nonfoil": ["3f1c2aba-e5f1-5ef8-8fd8-f5942fbd5aff", "4831adbb-c0af-5d27-b407-19f2f7805949", "c690e178-661d-5e17-9b29-a5bf6319a844"]}, "subtypes": ["Rat"], "supertypes": [], "text": "When this creature enters, target opponent discards a card.", "toughness": "1", "type": "Creature — Rat", "types": ["Creature"], "uuid": "f4cf6831-f6af-51c9-af91-1246830ae0fd"}, {"artist": "Chippy", "artistIds": ["a36f01a0-e51a-48b2-a556-b9b3bc73f969"], "availability": ["mtgo", "paper"], "boosterTypes": ["default"], "borderColor": "black", "colorIdentity": ["B"], "colors": ["B"], "convertedManaCost": 1.0, "count": 2, "edhrecRank": 25869, "edhrecSaltiness": 0.33, "finishes": ["nonfoil", "foil"], "flavorText": "\"Life is a circle. Death is a vicious circle.\"", "foreignData": [{"flavorText": "「生命是个循环。 死亡则是恶毒的循环。」", "identifiers": {"multiverseId": "173050", "scryfallId": "87407bf3-957c-4ebd-811f-d65b31b28f9a"}, "language": "Chinese Simplified", "multiverseId": 173050, "name": "窒烟学徒", "text": "每当任一牌手使用黑色咒语时，你可以支付{1}。 如果你如此作，则目标牌手失去1点生命。", "type": "生物～元素／祭师", "uuid": "145afc06-f75f-5297-af9a-f11c37f6d132"}, {"flavorText": "« La vie est un cercle. La mort est un cercle vicieux. »", "identifiers": {"multiverseId": "173351", "scryfallId": "7db2edd7-ef6f-43d3-8d28-49d4ce96acc8"}, "language": "French", "multiverseId": 173351, "name": "Adepte fumant", "text": "À chaque fois qu'un joueur joue un sort noir, vous pouvez payer {1}. Si vous faites ainsi, le joueur ciblé perd 1 point de vie.", "type": "Créature : élémental et shamane", "uuid": "0816690e-9f27-5c92-a6b6-8054fcd7f8b7"}, {"flavorText": "„Das Leben ist ein Kreis. Der Tod ist ein Teufelskreis.\"", "identifiers": {"multiverseId": "174555", "scryfallId": "a9ff057d-c1f4-41b8-bfda-e55503a59cc6"}, "language": "German", "multiverseId": 174555, "name": "Schwelender Novize", "text": "Immer wenn ein Spieler einen schwarzen Zauberspruch spielt, kannst du {1} bezahlen. Falls du dies tust, verliert ein Spieler deiner Wahl 1 Lebenspunkt.", "type": "Kreatur — Elementarwesen, Schamane", "uuid": "a420e51a-5298-55ef-8a23-4cdc32b08634"}, {"flavorText": "\"La vita è un circolo. La morte un circolo vizioso.\"", "identifiers": {"multiverseId": "173652", "scryfallId": "155d0ac9-2910-429b-a34e-bdf5ba929849"}, "language": "Italian", "multiverseId": 173652, "name": "Iniziato Ardente", "text": "Ogniqualvolta un giocatore gioca una magia nera, puoi pagare {1}. Se lo fai, un giocatore bersaglio perde 1 punto vita.", "type": "Creatura — Sciamano Elementale", "uuid": "7a6fe727-e368-5de5-ba08-31230e7212dc"}, {"flavorText": "「生は円を成す。 死は邪悪な円を成す。」", "identifiers": {"multiverseId": "173953", "scryfallId": "a4c30249-69dd-4321-ac91-7e52f476d439"}, "language": "Japanese", "multiverseId": 173953, "name": "薄煙の信徒", "text": "いずれかのプレイヤーが黒の呪文をプレイするたび、プレイヤー１人を対象とする。あなたは{1}を支払ってもよい。 そうした場合、そのプレイヤーは１点のライフを失う。", "type": "クリーチャー — エレメンタル・シャーマン", "uuid": "46eec0ab-c9d3-575c-9e1c-4b5d9018673f"}, {"flavorText": "\"A vida é um círculo. A morte é um círculo vicioso.\"", "identifiers": {"multiverseId": "172147", "scryfallId": "705c1096-6456-4a4c-b3b9-c422eb932668"}, "language": "Portuguese (Brazil)", "multiverseId": 172147, "name": "Iniciado Ignitor", "text": "Toda vez que um jogador joga uma mágica preta, você pode pagar {1}. Se fizer isso, o jogador alvo perderá 1 ponto de vida.", "type": "Criatura — Elemental Xamã", "uuid": "28e36f37-25e4-54bf-bf1f-53ee2cd7eb13"}, {"flavorText": "«Жизнь это круг. Смерть же порочный круг».", "identifiers": {"multiverseId": "172448", "scryfallId": "16ef32ab-c05f-4d4e-a398-6879fd4ae79f"}, "language": "Russian", "multiverseId": 172448, "name": "Искусный Поджигатель", "text": "Каждый раз, когда игрок разыгрывает черное заклинание, вы можете заплатить {1}. Если вы это делаете, целевой игрок теряет 1 жизнь.", "type": "Существо — Элементаль Шаман", "uuid": "20cd61f7-def0-50c1-b23a-b3e3e3c5c2f0"}, {"flavorText": "\"La vida es un círculo. La muerte es un círculo vicioso.\"", "identifiers": {"multiverseId": "172749", "scryfallId": "fbba7cdc-c53e-4e32-b528-d9d1bcffd71b"}, "language": "Spanish", "multiverseId": 172749, "name": "Iniciado humeante", "text": "Siempre que un jugador juegue un hechizo negro, puedes pagar {1}. Si lo haces, el jugador objetivo pierde 1 vida.", "type": "Criatura — Chamán elemental", "uuid": "0e5ccb05-4c30-5270-b310-365f5ddddcf4"}], "frameVersion": "2003", "hasFoil": true, "hasNonFoil": true, "identifiers": {"cardKingdomFoilId": "125016", "cardKingdomId": "124730", "cardsphereFoilId": "41491", "cardsphereId": "41492", "deckboxId": "3794", "mcmId": "19092", "mcmMetaId": "9642", "mtgjsonV4Id": "d2fe1d4c-380b-554e-9ff9-7c2323e3d6d2", "mtgoFoilId": "29524", "mtgoId": "29523", "multiverseId": "147376", "scryfallCardBackId": "0aeebaf5-8c7d-4636-9e82-8c27447861f7", "scryfallId": "16ecbed3-3a41-4823-8cd2-498daaaa0d4f", "scryfallIllustrationId": "78d9f17a-4134-4c01-aa2c-de32d9ec43f4", "scryfallOracleId": "0300d8a1-ff4e-4e05-a097-4822f80c47e1", "tcgplayerProductId": "18793"}, "isEtched": false, "isFoil": false, "language": "English", "layout": "normal", "legalities": {"commander": "Legal", "duel": "Legal", "legacy": "Legal", "modern": "Legal", "oathbreaker": "Legal", "pauper": "Legal", "paupercommander": "Legal", "penny": "Legal", "predh": "Legal", "vintage": "Legal"}, "manaCost": "{B}", "manaValue": 1.0, "name": "Smolder Initiate", "number": "78", "originalText": "Whenever a player plays a black spell, you may pay {1}. If you do, target player loses 1 life.", "power": "1", "printings": ["SHM"], "purchaseUrls": {"cardKingdom": "https://mtgjson.com/links/0bdc43cd53b974b1", "cardKingdomFoil": "https://mtgjson.com/links/7b21e3f2b4308f43", "cardmarket": "https://mtgjson.com/links/fe6e87e30ed73dcd", "tcgplayer": "https://mtgjson.com/links/4f9abc44073cdf79"}, "rarity": "common", "setCode": "SHM", "sourceProducts": {"foil": ["8d99f8c2-a0d4-5d5c-8dfa-1552a5f28103", "df9ec53c-cbe9-50c0-ad27-a94f6cc75812"], "nonfoil": ["2918db4d-2ca5-5a82-946b-2c9b236a53e7", "2b651e97-8239-5ccb-bcf9-5f88d09b2868", "3f1c2aba-e5f1-5ef8-8fd8-f5942fbd5aff", "a4082250-6a21-565d-992a-ed1bb74c10bc", "dc5253c6-cb4b-5a43-9659-2dd7d2920ec6", "df9ec53c-cbe9-50c0-ad27-a94f6cc75812"]}, "subtypes": ["Elemental", "Shaman"], "supertypes": [], "text": "Whenever a player casts a black spell, you may pay {1}. If you do, target player loses 1 life.", "toughness": "1", "type": "Creature — Elemental Shaman", "types": ["Creature"], "uuid": "87955378-3d18-5f56-ba0c-321a66bef355"}, {"artist": "Roger Raupp", "artistIds": ["79d6f296-1948-4a24-a2ce-a76e89057f23"], "availability": ["mtgo", "paper"], "boosterTypes": ["default"], "borderColor": "black", "colorIdentity": ["B"], "colors": ["B"], "convertedManaCost": 3.0, "count": 1, "edhrecRank": 18936, "finishes": ["nonfoil", "foil"], "flavorText": "One rarely notices a heartbeat, save when it is stolen.", "foreignData": [{"flavorText": "除非给偷走，否则人们很少注意到自己的心跳。", "identifiers": {"multiverseId": "147639", "scryfallId": "4d61b31b-6405-41e4-b444-3baa85746c54"}, "language": "Chinese Simplified", "multiverseId": 147639, "name": "折磨", "text": "目标生物得-1/-1直到回合结束。\n抓一张牌。", "type": "瞬间", "uuid": "fe9b79ea-9ef2-5a19-96d9-efb5863e0b23"}, {"flavorText": "L'affliction ne guérit pas le mal. —Proverbe français", "identifiers": {"multiverseId": "150058", "scryfallId": "38f05d17-60c9-4c03-8d54-d110abc5f114"}, "language": "French", "multiverseId": 150058, "name": "Affliction", "text": "La créature ciblée gagne -1/-1 jusqu'à la fin du tour.\nPiochez une carte.", "type": "Éphémère", "uuid": "e3ad7c5c-ada7-5006-983e-3ea4519d07c7"}, {"flavorText": "Einzelne Herzschläge bemerkt man selten — außer wenn sie einem gestohlen werden.", "identifiers": {"multiverseId": "148405", "scryfallId": "d3f5e1a3-7fbf-4d57-a5a7-e96c0ff649a3"}, "language": "German", "multiverseId": 148405, "name": "Leiden lassen", "text": "Eine Kreatur deiner Wahl erhält -1/-1 bis zum Ende des Zuges.\nZiehe eine Karte.", "type": "Spontanzauber", "uuid": "01d8e55f-6e4d-5581-978e-48bf8d47c561"}, {"flavorText": "Raramente si nota un battito del cuore, se non quando viene rubato.", "identifiers": {"multiverseId": "148788", "scryfallId": "e1cfdc88-9fc0-4b05-a8e0-224587f272a9"}, "language": "Italian", "multiverseId": 148788, "name": "Tormentare", "text": "Una creatura bersaglio prende -1/-1 fino alla fine del turno.\nPesca una carta.", "type": "Istantaneo", "uuid": "00545516-5c3e-5b4a-8a3e-d85a11f1c833"}, {"flavorText": "鼓動に気をかけるものはまずいない。それが奪われるまでは。", "identifiers": {"multiverseId": "148022", "scryfallId": "4548e4ef-d610-4c8d-b1e4-ed7c9aec94dd"}, "language": "Japanese", "multiverseId": 148022, "name": "苦悩", "text": "クリーチャー１体を対象とする。それはターン終了時まで－１/－１の修整を受ける。\nカードを１枚引く。", "type": "インスタント", "uuid": "aefa0b37-43a1-593e-b943-3dad7e432ce2"}, {"flavorText": "Raramente se nota um batimento cardíaco, a não ser quando este é roubado.", "identifiers": {"multiverseId": "149675", "scryfallId": "b51ca5d5-5669-4c57-b3a9-4889ea577060"}, "language": "Portuguese (Brazil)", "multiverseId": 149675, "name": "Afligir", "text": "A criatura alvo recebe -1/-1 até o final do turno.\nCompre um card.", "type": "Mágica Instantânea", "uuid": "0ebbb568-e92d-51b2-8d37-d76d2ad00c8b"}, {"flavorText": "Редко кто вспоминает о биении сердца, до тех пор пока оно вдруг не пропадет.", "identifiers": {"multiverseId": "149292", "scryfallId": "00ec9a07-ad1c-4ba5-96f4-bd37378324fe"}, "language": "Russian", "multiverseId": 149292, "name": "Страдание", "text": "Целевое существо получает -1/-1 до конца хода.\nВозьмите карту.", "type": "Мгновенное заклинание", "uuid": "9c749a86-5096-59d3-b9ba-96d359536950"}, {"flavorText": "Rara vez uno se percata de un latido, salvo cuando ya no está.", "identifiers": {"multiverseId": "150441", "scryfallId": "edf1150d-5f1c-4c1e-b543-61e9adc048be"}, "language": "Spanish", "multiverseId": 150441, "name": "Afligir", "text": "La criatura objetivo obtiene -1/-1 hasta el final del turno.\nRoba una carta.", "type": "Instantáneo", "uuid": "e124f851-0f68-58ae-a4ce-9fb27193760d"}], "frameVersion": "2003", "hasFoil": true, "hasNonFoil": true, "identifiers": {"cardKingdomFoilId": "123211", "cardKingdomId": "122843", "cardsphereFoilId": "7", "cardsphereId": "8", "deckboxId": "2999", "mcmId": "16289", "mcmMetaId": "66", "mtgjsonV4Id": "8774e18f-3752-5c06-af94-5da3960da9ed", "mtgoFoilId": "27483", "mtgoId": "27482", "multiverseId": "135206", "scryfallCardBackId": "0aeebaf5-8c7d-4636-9e82-8c27447861f7", "scryfallId": "20f18447-2853-469b-b3b3-20d6bcafa6e7", "scryfallIllustrationId": "83259a38-bbad-4dd1-bcd5-d1b1d96b0380", "scryfallOracleId": "471f6ad3-cf01-42dd-a519-ea8e13039fea", "tcgplayerProductId": "15026"}, "isEtched": false, "isFoil": false, "isReprint": true, "language": "English", "layout": "normal", "legalities": {"commander": "Legal", "duel": "Legal", "legacy": "Legal", "modern": "Legal", "oathbreaker": "Legal", "pauper": "Legal", "paupercommander": "Legal", "penny": "Legal", "predh": "Legal", "premodern": "Legal", "vintage": "Legal"}, "manaCost": "{2}{B}", "manaValue": 3.0, "name": "Afflict", "number": "125", "originalText": "Target creature gets -1/-1 until end of turn.\nDraw a card.", "printings": ["10E", "ODY"], "purchaseUrls": {"cardKingdom": "https://mtgjson.com/links/f482c95c918b9360", "cardKingdomFoil": "https://mtgjson.com/links/1e5ea78c0b988422", "cardmarket": "https://mtgjson.com/links/d4769234b08c2262", "tcgplayer": "https://mtgjson.com/links/2cfe3a25e6fa5d8a"}, "rarity": "common", "setCode": "10E", "sourceProducts": {"foil": ["c5cd29de-5ec9-5e13-b8eb-40e3a9f79f9a", "c690e178-661d-5e17-9b29-a5bf6319a844"], "nonfoil": ["3f1c2aba-e5f1-5ef8-8fd8-f5942fbd5aff", "4831adbb-c0af-5d27-b407-19f2f7805949", "c690e178-661d-5e17-9b29-a5bf6319a844"]}, "subtypes": [], "supertypes": [], "text": "Target creature gets -1/-1 until end of turn.\nDraw a card.", "type": "Instant", "types": ["Instant"], "uuid": "9acf4d13-d68f-5fec-93b4-caf0a14725a5"}, {"artist": "Dave Allsop", "artistIds": ["99b8310a-4fd6-4ded-8ab7-3b5185821cbe"], "availability": ["mtgo", "paper"], "boosterTypes": ["default"], "borderColor": "black", "colorIdentity": ["B"], "colors": ["B"], "convertedManaCost": 6.0, "count": 1, "edhrecRank": 9244, "finishes": ["nonfoil", "foil"], "flavorText": "There are things beneath the murk for whom the bog is a stew, a thin broth in need of meat.", "foreignData": [{"flavorText": "对藏身泥泞下之物来说，沼泽是锅无味淡汤，得加点肉才行。", "identifiers": {"multiverseId": "173034", "scryfallId": "82969c3f-86c1-4d36-baf6-f5391681c65e"}, "language": "Chinese Simplified", "multiverseId": 173034, "name": "腐化", "text": "腐化对目标生物或牌手造成伤害，其数量等同于由你操控的沼泽数量。 你获得等同于以此法所造成的伤害之生命。", "type": "法术", "uuid": "124c7d0f-917a-558f-aac4-fffaafa62c1c"}, {"flavorText": "Il y en a pour qui le marais n'est rien d'autre qu'un ragoût, un bouillon léger en manque de viande.", "identifiers": {"multiverseId": "173335", "scryfallId": "b687bb48-6e65-4c79-9995-db0a7bcb0468"}, "language": "French", "multiverseId": 173335, "name": "Corruption", "text": "La Corruption inflige à une cible, créature ou joueur, un nombre de blessures égal au nombre de marais que vous contrôlez. Vous gagnez autant de points de vie que de blessures infligées de cette manière.", "type": "Rituel", "uuid": "668d57ce-830f-52c5-a7ac-a97dbe40d69e"}, {"flavorText": "Im trüben Wasser warten Wesen, für die der Nebel ein Eintopf ist, eine dünne Brühe, die dringend mehr Fleisch benötigt.", "identifiers": {"multiverseId": "174539", "scryfallId": "570cf904-af48-4ea6-aa48-a8eaea5e2f7f"}, "language": "German", "multiverseId": 174539, "name": "Korruption", "text": "Korruption fügt einer Kreatur oder einem Spieler deiner Wahl Schadenspunkte in Höhe der Anzahl der Sümpfe, die du kontrollierst, zu. Du erhältst so viele Lebenspunkte dazu, wie auf diese Weise Schadenspunkte zugefügt wurden.", "type": "Hexerei", "uuid": "04ee8a10-54ae-50f6-a7fc-3e42995699e8"}, {"flavorText": "Ci sono cose nell'oscurità per le quali la palude è un grosso stufato, un povero brodo in cerca di carne.", "identifiers": {"multiverseId": "173636", "scryfallId": "1fb7a0f8-2e22-45a3-ab9d-406296455bb8"}, "language": "Italian", "multiverseId": 173636, "name": "Corrompere", "text": "Corrompere infligge danno pari al numero di Paludi che controlli a una creatura o a un giocatore bersaglio. Guadagni punti vita pari ai danni inflitti in questo modo.", "type": "Stregoneria", "uuid": "4589e1e3-32e2-54dc-b4b1-a18830b0ff62"}, {"flavorText": "暗黒の中に潜むものにとって、泥沼は肉の足りない薄い出汁のシチューのようなものだ。", "identifiers": {"multiverseId": "173937", "scryfallId": "0148211f-c7d1-4613-9892-e3a99d45264b"}, "language": "Japanese", "multiverseId": 173937, "name": "堕落", "text": "クリーチャー１体かプレイヤー１人を対象とする。堕落はそれに、あなたがコントロールする沼の総数に等しい点数のダメージを与える。 あなたはこれにより与えたダメージに等しい点数のライフを得る。", "type": "ソーサリー", "uuid": "a74dc206-0f54-55c0-b07e-f550d56b65e7"}, {"flavorText": "Na escuridão há seres para os quais o pântano é um ensopado, um caldo ralo que precisa de carne.", "identifiers": {"multiverseId": "172131", "scryfallId": "a8bffbfc-bc79-467c-8896-01ef10105612"}, "language": "Portuguese (Brazil)", "multiverseId": 172131, "name": "Corromper", "text": "Corromper causa à criatura ou ao jogador alvo dano igual ao número de Pântanos que você controla. Você ganha uma quantidade de pontos de vida igual ao dano causado desta maneira.", "type": "Feitiço", "uuid": "40301908-d060-542d-85c7-4f1350859dbb"}, {"flavorText": "В черной трясине обитают твари, для которых болото это варево, жиденькая похлебка, в которой явно не хватает мяса.", "identifiers": {"multiverseId": "172432", "scryfallId": "895f6153-9cc0-4fc3-995f-70fb32cae2bc"}, "language": "Russian", "multiverseId": 172432, "name": "Разложение", "text": "Разложение наносит целевому существу или игроку повреждения, равные количеству Болот под вашим контролем. Вы получаете столько жизней, сколько повреждений было нанесено таким образом.", "type": "Волшебство", "uuid": "9ab84935-7884-5a93-b53d-2ea33e4a2ee9"}, {"flavorText": "Hay cosas bajo el fango para los cuales el pantano es un caldo soso que necesita carne.", "identifiers": {"multiverseId": "172733", "scryfallId": "4d72d16e-d551-482e-8d88-6ff67c40dd6a"}, "language": "Spanish", "multiverseId": 172733, "name": "Corromper", "text": "Corromper hace una cantidad de daño igual al número de pantanos que controles a la criatura o jugador objetivo. Ganas una cantidad de vida igual al daño hecho de esta manera.", "type": "Conjuro", "uuid": "482b9d82-1c4c-5ee3-966d-02fdbc2aada3"}], "frameVersion": "2003", "hasFoil": true, "hasNonFoil": true, "identifiers": {"cardKingdomFoilId": "124824", "cardKingdomId": "124538", "cardsphereFoilId": "41074", "cardsphereId": "41075", "deckboxId": "7322", "mcmId": "19076", "mcmMetaId": "1149", "mtgjsonV4Id": "cea00901-bdfb-5bb5-84f6-64d119397b8c", "mtgoFoilId": "29420", "mtgoId": "29419", "multiverseId": "146013", "scryfallCardBackId": "0aeebaf5-8c7d-4636-9e82-8c27447861f7", "scryfallId": "f3504249-d226-4a9a-8855-69723cefaeff", "scryfallIllustrationId": "799f9ee6-e26b-4eef-8922-6d3a6b2c9686", "scryfallOracleId": "a88a1c53-7de3-423a-a95a-24ed5666ab96", "tcgplayerProductId": "18594"}, "isEtched": false, "isFoil": false, "isReprint": true, "language": "English", "layout": "normal", "legalities": {"brawl": "Legal", "commander": "Legal", "duel": "Legal", "gladiator": "Legal", "historic": "Legal", "legacy": "Legal", "modern": "Legal", "oathbreaker": "Legal", "pauper": "Legal", "paupercommander": "Legal", "penny": "Legal", "pioneer": "Legal", "predh": "Legal", "premodern": "Legal", "timeless": "Legal", "vintage": "Legal"}, "manaCost": "{5}{B}", "manaValue": 6.0, "name": "Corrupt", "number": "62", "originalText": "Corrupt deals damage equal to the number of Swamps you control to target creature or player. You gain life equal to the damage dealt this way.", "printings": ["7ED", "BRO", "DDC", "DDD", "DVD", "GVL", "M11", "M14", "P08", "PIDW", "PLST", "PRM", "SHM", "USG"], "purchaseUrls": {"cardKingdom": "https://mtgjson.com/links/6cba9858e57ce25f", "cardKingdomFoil": "https://mtgjson.com/links/7c4a29c836262214", "cardmarket": "https://mtgjson.com/links/923852deff57fe35", "tcgplayer": "https://mtgjson.com/links/45741be9a8a5b31e"}, "rarity": "uncommon", "rulings": [{"date": "2004-10-04", "text": "The swamps are counted on resolution."}, {"date": "2010-08-15", "text": "The amount of damage dealt to a creature is not bounded by its toughness, and the amount of damage dealt to a player is not bounded by that player's life total. For example, if Corrupt deals 6 damage to a 2/2 creature, you'll gain 6 life."}, {"date": "2010-08-15", "text": "The life you gain is equal to the damage dealt by Corrupt, not necessarily to the number of Swamps you control (if some or all of the damage is prevented, for example)."}, {"date": "2013-07-01", "text": "Corrupt counts any land you control with the subtype Swamp, not just ones named Swamp."}, {"date": "2022-10-14", "text": "Corrupt counts any land you control with the subtype Swamp, not just ones named Swamp."}], "setCode": "SHM", "sourceProducts": {"foil": ["8d99f8c2-a0d4-5d5c-8dfa-1552a5f28103", "df9ec53c-cbe9-50c0-ad27-a94f6cc75812"], "nonfoil": ["2b651e97-8239-5ccb-bcf9-5f88d09b2868", "3f1c2aba-e5f1-5ef8-8fd8-f5942fbd5aff", "dc5253c6-cb4b-5a43-9659-2dd7d2920ec6", "df9ec53c-cbe9-50c0-ad27-a94f6cc75812"]}, "subtypes": [], "supertypes": [], "text": "Corrupt deals damage to any target equal to the number of Swamps you control. You gain life equal to the damage dealt this way.", "type": "Sorcery", "types": ["Sorcery"], "uuid": "cf79b6bc-5167-5e9d-a850-22cbf9efdbef"}, {"artist": "Michael Sutfin", "artistIds": ["5ce7b3bd-53d2-49e6-b504-37191e8e9b17"], "availability": ["mtgo", "paper"], "boosterTypes": ["default"], "borderColor": "black", "colorIdentity": ["B"], "colors": ["B"], "convertedManaCost": 2.0, "count": 1, "edhrecRank": 17444, "edhrecSaltiness": 1.0, "finishes": ["nonfoil", "foil"], "flavorText": "\"They say the eyes are the windows to the soul. I like to break windows and take what's inside.\"\n—Braids, dementia summoner", "foreignData": [{"flavorText": "「话说眼睛是灵魂之窗。 我倒挺喜欢打破窗子往里瞧。」 ～惧像召唤师布蕾德", "identifiers": {"multiverseId": "147714", "scryfallId": "8a9e7bdc-9807-4865-8bfd-d442b77cc98c"}, "language": "Chinese Simplified", "multiverseId": 147714, "name": "苦痛", "text": "目标牌手展示其手牌。 你选择其中一张非地的牌。 该牌手弃掉该牌。", "type": "法术", "uuid": "ed09572a-4925-5b6e-b7b6-d8229003674c"}, {"flavorText": "« On dit que les yeux sont le miroir de l'âme. Autant le briser pour prendre ce qui se trouve derrière. » —Nattes, invocatrice de démences", "identifiers": {"multiverseId": "150069", "scryfallId": "cdecf4fd-327e-464d-8c0d-2daac50896ee"}, "language": "French", "multiverseId": 150069, "name": "Détresse", "text": "Le joueur ciblé révèle sa main. Choisissez-y une carte non-terrain. Ce joueur se défausse de cette carte.", "type": "Rituel", "uuid": "4caadb83-7ef2-5a22-b4ec-d27ab5690df0"}, {"flavorText": "„Es heißt, die Augen seien die Fenster der Seele. Ich schlage gerne Fenster ein und hole mir, was dahinter liegt.\" —Braids, Wahnwitzbeschwörerin", "identifiers": {"multiverseId": "148480", "scryfallId": "a2a3e8ab-f3da-4b0b-afff-b8a679ac8410"}, "language": "German", "multiverseId": 148480, "name": "Kummer", "text": "Ein Spieler deiner Wahl zeigt die Karten auf seiner Hand offen vor. Du bestimmst eine Nichtländerkarte darunter. Dieser Spieler wirft diese Karte ab.", "type": "Hexerei", "uuid": "464cb2c0-5867-5530-8beb-36d5cd912729"}, {"flavorText": "\"Dicono che gli occhi sono la finestra dell'anima. Mi piace infrangere le finestre per prendere quel che c'è all'interno.\" —Braids, evocatrice di demenza", "identifiers": {"multiverseId": "148863", "scryfallId": "d3b7623e-8a37-4327-8469-c8c17d782bc7"}, "language": "Italian", "multiverseId": 148863, "name": "Angoscia", "text": "Un giocatore bersaglio rivela la sua mano. Scegli una carta non terra da quella mano. Quel giocatore scarta quella carta.", "type": "Stregoneria", "uuid": "5adb4900-d4b4-54f8-a87d-a734f0fe484a"}, {"flavorText": "目は心の窓だなんていうわね。 私はその窓をぶち壊して中身を取り出すほうが好きだわ。 ――狂気を招く者ブレイズ", "identifiers": {"multiverseId": "148097", "scryfallId": "9a18c5d4-8697-4f99-bf40-b8fee4aa503c"}, "language": "Japanese", "multiverseId": 148097, "name": "困窮", "text": "プレイヤー１人を対象とする。そのプレイヤーは手札を公開する。 その中の土地でないカードを１枚選ぶ。 そのプレイヤーはそのカードを捨てる。", "type": "ソーサリー", "uuid": "64220ed2-148c-59e6-84f3-f243414a45c7"}, {"flavorText": "\"Dizem que os olhos são as janelas da alma. Eu gosto de quebrar janelas e pegar o que há dentro.\" — Braids, invocadora da demência", "identifiers": {"multiverseId": "149686", "scryfallId": "b694a09e-7049-4b0e-9389-b0a9c3e1fa5e"}, "language": "Portuguese (Brazil)", "multiverseId": 149686, "name": "Extenuar", "text": "O jogador alvo revela sua própria mão. Você escolhe um card que não seja um terreno da mão dele. Aquele jogador descarta aquele card.", "type": "Feitiço", "uuid": "86a36017-d85f-5319-94c7-5105ccc4bd34"}, {"flavorText": "\"Говорят, что глаза это окна души. Мне нравится разбивать окна и разорять дома\". — Брейдс, призывающая слабоумие", "identifiers": {"multiverseId": "149303", "scryfallId": "266fb26b-79f8-4c5b-aba8-c9f9ba298023"}, "language": "Russian", "multiverseId": 149303, "name": "Разорение", "text": "Целевой игрок показывает свою руку. Выберите из нее карту, не являющуюся землей. Тот игрок сбрасывает ту карту.", "type": "Волшебство", "uuid": "50f36c76-ac2f-53f0-be7c-e1d2d94989e2"}, {"flavorText": "\"Dicen que los ojos son ventanas hacia el alma. Me gusta romper ventanas y tomar lo que hay dentro.\" —Trenzas, invocadora de demencia", "identifiers": {"multiverseId": "150452", "scryfallId": "253cfd0a-ec9e-4755-8aba-efa2598921a2"}, "language": "Spanish", "multiverseId": 150452, "name": "Acosar", "text": "El jugador objetivo muestra su mano. Tú eliges de ahí una carta que no sea tierra. Ese jugador descarta esa carta.", "type": "Conjuro", "uuid": "7f0fcd53-1c14-5a31-81db-ce02a8806478"}], "frameVersion": "2003", "hasFoil": true, "hasNonFoil": true, "identifiers": {"cardKingdomFoilId": "123222", "cardKingdomId": "122854", "cardsphereFoilId": "157", "cardsphereId": "158", "deckboxId": "3013", "mcmId": "16300", "mcmMetaId": "6971", "mtgjsonV4Id": "06174318-8c83-5592-a3f7-af87fb9fbd41", "mtgoFoilId": "27658", "mtgoId": "27657", "multiverseId": "135219", "scryfallCardBackId": "0aeebaf5-8c7d-4636-9e82-8c27447861f7", "scryfallId": "1ebb7ade-ebbb-49fb-b64f-fa247f9a9af6", "scryfallIllustrationId": "93aed334-9db2-440d-af71-541501410e43", "scryfallOracleId": "7bb1b48b-aa6b-4064-9355-c43b0f509388", "tcgplayerProductId": "15101"}, "isEtched": false, "isFoil": false, "isReprint": true, "language": "English", "layout": "normal", "legalities": {"commander": "Legal", "duel": "Legal", "legacy": "Legal", "modern": "Legal", "oathbreaker": "Legal", "pauper": "Legal", "paupercommander": "Legal", "penny": "Legal", "predh": "Legal", "vintage": "Legal"}, "manaCost": "{B}{B}", "manaValue": 2.0, "name": "Distress", "number": "136", "originalText": "Target player reveals his or her hand. You choose a nonland card from it. That player discards that card.", "printings": ["10E", "CHK", "M12"], "purchaseUrls": {"cardKingdom": "https://mtgjson.com/links/ef831da6c0104d09", "cardKingdomFoil": "https://mtgjson.com/links/fa1339ab168f41b6", "cardmarket": "https://mtgjson.com/links/381faa6b586551f7", "tcgplayer": "https://mtgjson.com/links/3e8199e0507d2ed6"}, "rarity": "common", "rulings": [{"date": "2014-02-01", "text": "If you target yourself with this spell, you must reveal your entire hand to the other players just as any other player would."}], "setCode": "10E", "sourceProducts": {"foil": ["c5cd29de-5ec9-5e13-b8eb-40e3a9f79f9a", "c690e178-661d-5e17-9b29-a5bf6319a844"], "nonfoil": ["3f1c2aba-e5f1-5ef8-8fd8-f5942fbd5aff", "4831adbb-c0af-5d27-b407-19f2f7805949", "c690e178-661d-5e17-9b29-a5bf6319a844"]}, "subtypes": [], "supertypes": [], "text": "Target player reveals their hand. You choose a nonland card from it. That player discards that card.", "type": "Sorcery", "types": ["Sorcery"], "uuid": "77ce01d6-3609-519e-a0d4-6ad6770c45e4"}, {"artist": "Jim Nelson", "artistIds": ["aa9f64d1-29e1-4c82-877e-44c18183f40b"], "availability": ["mtgo", "paper"], "boosterTypes": ["default"], "borderColor": "black", "colorIdentity": ["B"], "colors": ["B"], "convertedManaCost": 5.0, "count": 2, "edhrecRank": 25121, "edhrecSaltiness": 0.31, "finishes": ["nonfoil", "foil"], "flavorText": "\"The elves are right: Death inevitably leads to life. But the truly powerful don't just experience this cycle. They control it.\"\n—Crovax, ascendant evincar", "foreignData": [{"flavorText": "「地精是对的：死亡必将引领新生。 但真强者不只能体验此循环，还能一手掌控。」 ～天威大魔将寇维克斯", "identifiers": {"multiverseId": "147730", "scryfallId": "60699e21-05ba-48a8-86c1-c1dbb3ef49eb"}, "language": "Chinese Simplified", "multiverseId": 147730, "name": "吸取精华", "text": "吸取精华对目标生物或牌手造成3点伤害，且你获得3点生命。", "type": "法术", "uuid": "b04a1791-0c66-5e63-9a21-994f09e18de8"}, {"flavorText": "« Les elfes ont raison : la mort conduit inévitablement à la vie. Mais les puissants de ce monde ne sont pas les victimes de ce cycle. Ils le contrôlent. » — Crovax, incarmal", "identifiers": {"multiverseId": "150074", "scryfallId": "28184f95-52f3-4418-9485-04cb5d8c4409"}, "language": "French", "multiverseId": 150074, "name": "Drain d'essence", "text": "Le Drain d'essence inflige 3 blessures à une cible, créature ou joueur, et vous gagnez 3 points de vie.", "type": "Rituel", "uuid": "73c9f5ab-c12a-5960-afd3-623a9e05727b"}, {"flavorText": "„Die Elfen haben Recht: Aus dem Tod entsteht neues Leben. Aber die Mächtigsten müssen diesen Zyklus nicht durchlaufen. Sie kontrollieren ihn stattdessen.\" —Crovax, aufsteigender Evincar", "identifiers": {"multiverseId": "148496", "scryfallId": "1a915267-ad83-4074-96e5-5acae53415e4"}, "language": "German", "multiverseId": 148496, "name": "Essenzentzug", "text": "Der Essenzentzug fügt einer Kreatur oder einem Spieler deiner Wahl 3 Schadenspunkte zu, und du erhältst 3 Lebenspunkte dazu.", "type": "Hexerei", "uuid": "e14403cc-81b3-5799-a2d3-6fbc79e7d0b1"}, {"flavorText": "\"Gli elfi hanno ragione: la Morte inevitabilmente porta alla vita. Ma quelli realmente possenti non fanno esperienza di questo ciclo. Piuttosto lo controllano.\" —Crovax, evincaro dominante", "identifiers": {"multiverseId": "148879", "scryfallId": "8bcfd9b1-e2db-4809-a60a-97793edc9ace"}, "language": "Italian", "multiverseId": 148879, "name": "Risucchia Essenza", "text": "Risucchia Essenza infligge 3 danni a una creatura o a un giocatore bersaglio e tu guadagni 3 punti vita.", "type": "Stregoneria", "uuid": "639661e6-ee8c-5c68-83a2-93eb1cc55866"}, {"flavorText": "エルフの言うことは正しい。死は結局生へとつながっていく。 しかし、真の強さはその周期を理解することではない。 それを支配することだ。 ――隆盛なるエヴィンカー、クロウヴァクス", "identifiers": {"multiverseId": "148113", "scryfallId": "79974b22-3fe2-4a83-9c90-4431ec7cebf1"}, "language": "Japanese", "multiverseId": 148113, "name": "本質の吸収", "text": "クリーチャー１体かプレイヤー１人を対象とする。本質の吸収はそれに３点のダメージを与え、あなたは３点のライフを得る。", "type": "ソーサリー", "uuid": "6cfe32a1-504f-5d39-8fca-18a069f52c44"}, {"flavorText": "\"Os elfos estão certos: a morte leva inevitavelmente à vida. Mas os realmente poderosos não experimentam simplesmente este ciclo. Eles o controlam.\" — Crovax, evincar ascendente", "identifiers": {"multiverseId": "149691", "scryfallId": "fc08ab7a-18ee-4eaa-b4fa-3d1d6ec0fb09"}, "language": "Portuguese (Brazil)", "multiverseId": 149691, "name": "Drenar Essência", "text": "Drenar Essência causa 3 pontos de dano à criatura ou ao jogador alvo e você ganha 3 pontos de vida.", "type": "Feitiço", "uuid": "7d96cd73-b26d-5179-a342-3df43f731452"}, {"flavorText": "\"Эльфы правы: смерть неизбежно ведет к жизни. Но те, кто обладают истинной властью, не проходят через этот цикл пассивно. Они им управляют\". — Кровакс, правящий эвинкар", "identifiers": {"multiverseId": "149308", "scryfallId": "b32acd16-debc-4285-933c-e06802c14bb5"}, "language": "Russian", "multiverseId": 149308, "name": "Утечка Эссенции", "text": "Утечка Эссенции наносит 3 повреждения целевому существу или игроку, а вы получаете 3 жизни.", "type": "Волшебство", "uuid": "7ef19c21-e579-5e64-b0d7-f26c303efa51"}, {"flavorText": "\"Los elfos están en lo cierto: la muerte lleva inevitablemente a la vida. Pero los poderosos no se sientan a experimentar el ciclo. Lo controlan.\" —Crovax, évincar predominante", "identifiers": {"multiverseId": "150457", "scryfallId": "ad718dba-f27c-4eb9-8142-557650162777"}, "language": "Spanish", "multiverseId": 150457, "name": "Drenaje de esencia", "text": "El Drenaje de esencia hace 3 puntos de daño a la criatura o jugador objetivo y tú ganas 3 vidas.", "type": "Conjuro", "uuid": "c1187dbd-5278-50a5-a523-979a69f47d6d"}], "frameVersion": "2003", "hasFoil": true, "hasNonFoil": true, "identifiers": {"cardKingdomFoilId": "123227", "cardKingdomId": "122859", "cardsphereFoilId": "190", "cardsphereId": "191", "deckboxId": "2977", "mcmId": "16305", "mcmMetaId": "1866", "mtgjsonV4Id": "4ecc7bcd-e6d7-5df2-8107-dde53faaaa58", "mtgoFoilId": "27015", "mtgoId": "27014", "multiverseId": "135191", "scryfallCardBackId": "0aeebaf5-8c7d-4636-9e82-8c27447861f7", "scryfallId": "8af61c18-a7ac-42c8-a942-d2f546c1ef57", "scryfallIllustrationId": "1fb952b6-5928-4892-a5ef-c06411c66c17", "scryfallOracleId": "4bf5402f-7bba-4c0c-aebd-1b231768f2b2", "tcgplayerProductId": "15117"}, "isEtched": false, "isFoil": false, "isReprint": true, "language": "English", "layout": "normal", "legalities": {"commander": "Legal", "duel": "Legal", "legacy": "Legal", "modern": "Legal", "oathbreaker": "Legal", "pauper": "Legal", "paupercommander": "Legal", "penny": "Legal", "predh": "Legal", "vintage": "Legal"}, "manaCost": "{4}{B}", "manaValue": 5.0, "name": "Essence Drain", "number": "141", "originalText": "Essence Drain deals 3 damage to target creature or player and you gain 3 life.", "printings": ["10E", "DPA", "DST", "M13", "PS11"], "purchaseUrls": {"cardKingdom": "https://mtgjson.com/links/3587ad9995808f39", "cardKingdomFoil": "https://mtgjson.com/links/22bfa8a911d83588", "cardmarket": "https://mtgjson.com/links/cb7790bb302666e1", "tcgplayer": "https://mtgjson.com/links/4a2cff0fd422013b"}, "rarity": "common", "rulings": [{"date": "2012-07-01", "text": "If the target permanent or player is an illegal target when Essence Drain tries to resolve, it won’t resolve and none of its effects will happen. You won’t gain 3 life."}], "setCode": "10E", "sourceProducts": {"foil": ["c5cd29de-5ec9-5e13-b8eb-40e3a9f79f9a", "c690e178-661d-5e17-9b29-a5bf6319a844"], "nonfoil": ["3f1c2aba-e5f1-5ef8-8fd8-f5942fbd5aff", "4831adbb-c0af-5d27-b407-19f2f7805949", "5b668c61-62fa-572a-ab0d-19234b47614e", "a26ac54c-2f36-5245-a82f-87fd7c84c0f3", "c690e178-661d-5e17-9b29-a5bf6319a844", "ff67afca-f016-5399-83b0-9f9f6e14f950"]}, "subtypes": [], "supertypes": [], "text": "Essence Drain deals 3 damage to any target and you gain 3 life.", "type": "Sorcery", "types": ["Sorcery"], "uuid": "d38298f2-29e8-57b0-b978-140aa2171cce"}, {"artist": "Zoltan Boros & Gabor Szikszai", "artistIds": ["1885e6cb-c827-4896-994e-3d0a027d602f", "44c3877f-8771-43dc-9e40-f4c765f59d2e"], "availability": ["mtgo", "paper"], "boosterTypes": ["default"], "borderColor": "black", "colorIdentity": ["B"], "colors": ["B"], "convertedManaCost": 5.0, "count": 1, "edhrecRank": 28987, "edhrecSaltiness": 0.07, "finishes": ["nonfoil", "foil"], "flavorText": "Death stings the victim only once, but those left behind feel the pain of loss with every passing memory.", "foreignData": [{"flavorText": "死亡只让遭难者痛苦一次，而每个逝去的记忆却让幸存者不断感受失落之苦痛。", "identifiers": {"multiverseId": "173039", "scryfallId": "e3952819-638a-42ed-86d9-26f4f1e36620"}, "language": "Chinese Simplified", "multiverseId": 173039, "name": "阴暗矛刺", "text": "消灭目标生物。 如果该生物是绿色或白色，则其操控者弃一张牌。", "type": "法术", "uuid": "189c7b0a-5616-5153-ac11-ed1531efd482"}, {"flavorText": "La mort ne frappe sa victime qu'une fois, mais ceux qui restent souffrent avec chaque souvenir de cette perte.", "identifiers": {"multiverseId": "173340", "scryfallId": "5ec27e73-7173-4b3a-a049-227b396a7962"}, "language": "French", "multiverseId": 173340, "name": "Lance de noirceur", "text": "Détruisez la créature ciblée. Si cette créature était verte ou blanche, son contrôleur se défausse d'une carte.", "type": "Rituel", "uuid": "4ab5f93f-197d-5c96-984c-f767918682b9"}, {"flavorText": "Jedes Opfer stirbt nur einmal, doch die Hinterbliebenen fühlen den Schmerz bei jeder Erinnerung neu.", "identifiers": {"multiverseId": "174544", "scryfallId": "e9d6432d-9221-4d13-8511-49a16689317b"}, "language": "German", "multiverseId": 174544, "name": "Düsterlanze", "text": "Zerstöre eine Kreatur deiner Wahl. Falls diese Kreatur grün oder weiß war, wirft ihr Beherrscher eine Karte aus der Hand ab.", "type": "Hexerei", "uuid": "4def3701-f386-5958-a3e0-9c4143238226"}, {"flavorText": "La morte colpisce le vittime una sola volta, ma i loro cari sentono il dolore della perdita in ogni ricordo del caduto.", "identifiers": {"multiverseId": "173641", "scryfallId": "638e6f29-0e96-49f3-9213-9b9c3f3a7141"}, "language": "Italian", "multiverseId": 173641, "name": "Lancia di Tenebra", "text": "Distruggi una creatura bersaglio. Se quella creatura era verde o bianca, il suo controllore scarta una carta.", "type": "Stregoneria", "uuid": "4a1779f9-d2c2-560f-8f98-497bee5d0973"}, {"flavorText": "死が獲物を刺すのは一度だけだが、残された者達は、思い出が通り過ぎるたびに失ったものへの苦痛を感じ続ける。", "identifiers": {"multiverseId": "173942", "scryfallId": "ad0a77ee-ea78-4620-9fb7-97bf71d38b75"}, "language": "Japanese", "multiverseId": 173942, "name": "憂鬱の槍", "text": "クリーチャー１体を対象とし、それを破壊する。 そのクリーチャーが白か緑である場合、それのコントローラーはカードを１枚捨てる。", "type": "ソーサリー", "uuid": "8e9a80fd-2706-5948-93b3-c5f53d1136b4"}, {"flavorText": "A morte aferroa a vítima apenas uma vez, mas os que ficam sentem a dor da perda a cada recordação.", "identifiers": {"multiverseId": "172136", "scryfallId": "1f238b97-32fa-4574-8f18-60f76a23e820"}, "language": "Portuguese (Brazil)", "multiverseId": 172136, "name": "Lança das Trevas", "text": "Destrua a criatura alvo. Se aquela criatura for verde ou branca, seu controlador descartará um card.", "type": "Feitiço", "uuid": "7514fa24-32e4-505c-8f94-c8790966c167"}, {"flavorText": "Смерть пронзает жертву один лишь раз, но те, кто остается позади, чувствуют боль потери при каждом воспоминании.", "identifiers": {"multiverseId": "172437", "scryfallId": "3706760f-5d4b-4e2b-b3ea-b4aaa293024d"}, "language": "Russian", "multiverseId": 172437, "name": "Копье Мрака", "text": "Уничтожьте целевое существо. Если то существо было зеленым или белым, контролирующий его игрок сбрасывает карту.", "type": "Волшебство", "uuid": "8067c89c-bb82-58cd-9fc5-210ae19da3e8"}, {"flavorText": "La muerte toca a su víctima sólo una vez, pero aquellos que quedan atrás sienten el dolor de la pérdida con cada recuerdo.", "identifiers": {"multiverseId": "172738", "scryfallId": "b6edaa68-9354-4dd1-8d80-dd140e8c2b34"}, "language": "Spanish", "multiverseId": 172738, "name": "Lanza lúgubre", "text": "Destruye la criatura objetivo. Si esa criatura era verde o blanca, su controlador descarta una carta.", "type": "Conjuro", "uuid": "16e63303-4284-554e-800c-1926a1ab5e50"}], "frameVersion": "2003", "hasFoil": true, "hasNonFoil": true, "identifiers": {"cardKingdomFoilId": "124876", "cardKingdomId": "124590", "cardsphereFoilId": "41190", "cardsphereId": "41191", "deckboxId": "4619", "mcmId": "19081", "mcmMetaId": "9631", "mtgjsonV4Id": "a61834bc-bb8a-5c5f-b68f-5ae49f6f3218", "mtgoFoilId": "29818", "mtgoId": "29817", "multiverseId": "158757", "scryfallCardBackId": "0aeebaf5-8c7d-4636-9e82-8c27447861f7", "scryfallId": "7b45bfb2-7c48-4da5-a0fd-29d353221814", "scryfallIllustrationId": "e9c9264e-e1cf-4f55-b1ce-d8a5f2be1b6c", "scryfallOracleId": "2aa040d2-35a1-4b1d-9542-395e1b8a9fd8", "tcgplayerProductId": "18647"}, "isEtched": false, "isFoil": false, "language": "English", "layout": "normal", "legalities": {"commander": "Legal", "duel": "Legal", "legacy": "Legal", "modern": "Legal", "oathbreaker": "Legal", "pauper": "Legal", "paupercommander": "Legal", "predh": "Legal", "vintage": "Legal"}, "manaCost": "{3}{B}{B}", "manaValue": 5.0, "name": "Gloomlance", "number": "67", "originalText": "Destroy target creature. If that creature was green or white, its controller discards a card.", "printings": ["SHM"], "purchaseUrls": {"cardKingdom": "https://mtgjson.com/links/258aaf2bff6d7988", "cardKingdomFoil": "https://mtgjson.com/links/0b41c58dab17e015", "cardmarket": "https://mtgjson.com/links/1c70c80ef168d20d", "tcgplayer": "https://mtgjson.com/links/8ce561d020f55fb6"}, "rarity": "common", "setCode": "SHM", "sourceProducts": {"foil": ["8d99f8c2-a0d4-5d5c-8dfa-1552a5f28103", "df9ec53c-cbe9-50c0-ad27-a94f6cc75812"], "nonfoil": ["2b651e97-8239-5ccb-bcf9-5f88d09b2868", "3f1c2aba-e5f1-5ef8-8fd8-f5942fbd5aff", "81739fd5-ec33-55ea-8817-e5834373b8a4", "dc5253c6-cb4b-5a43-9659-2dd7d2920ec6", "df9ec53c-cbe9-50c0-ad27-a94f6cc75812", "ea7263dd-e8b2-5622-bff7-9516d1ee8e51"]}, "subtypes": [], "supertypes": [], "text": "Destroy target creature. If that creature was green or white, its controller discards a card.", "type": "Sorcery", "types": ["Sorcery"], "uuid": "2b0a22ce-178a-5f92-a01b-75a366224fa1"}, {"artist": "Steve Luke", "artistIds": ["e2b0133e-a28d-45d1-8843-26285b41d61d"], "availability": ["mtgo", "paper"], "boosterTypes": ["default"], "borderColor": "black", "colorIdentity": ["B"], "colors": ["B"], "convertedManaCost": 3.0, "count": 2, "edhrecRank": 12223, "edhrecSaltiness": 0.41, "finishes": ["nonfoil", "foil"], "flavorText": "\"The beauty of mental attacks is that your victims never remember them.\"\n—Volrath", "foreignData": [{"flavorText": "「精神攻击最美妙之处，就是中招者根本不记得自己中了招。」 ～瓦拉司", "identifiers": {"multiverseId": "147831", "scryfallId": "e42575c7-c616-494f-8dee-bdb9ff1aeea1"}, "language": "Chinese Simplified", "multiverseId": 147831, "name": "心之衰", "text": "目标牌手弃两张牌。", "type": "法术", "uuid": "ef53d284-dab4-5239-9a98-9c48e714ca08"}, {"flavorText": "« La beauté des attaques mentales, c'est que vos victimes ne s'en souviennent jamais. » —Wöhlrajh", "identifiers": {"multiverseId": "150092", "scryfallId": "a264da13-894e-4403-8730-08cfb04f298c"}, "language": "French", "multiverseId": 150092, "name": "Pourrissement cérébral", "text": "Le joueur ciblé se défausse de deux cartes.", "type": "Rituel", "uuid": "99c0a199-db28-51ff-aa91-4d896082ae51"}, {"flavorText": "„Das Elegante an Angriffen auf die Erinnerung ist, dass deine Opfer sich nie daran erinnern können.\" —Volrath", "identifiers": {"multiverseId": "148597", "scryfallId": "fba41b85-6d35-4878-b1c6-41c110372edb"}, "language": "German", "multiverseId": 148597, "name": "Gedankenzersetzung", "text": "Ein Spieler deiner Wahl wirft zwei Karten aus seiner Hand ab.", "type": "Hexerei", "uuid": "ab7e2f60-582d-507c-bb7c-5d0638fbd194"}, {"flavorText": "\"Il bello degli attacchi mentali è che le tue vittime non possono ricordarsene.\" —Volrath", "identifiers": {"multiverseId": "148980", "scryfallId": "fd2af3ae-10df-491f-9bc2-28beb80db0fe"}, "language": "Italian", "multiverseId": 148980, "name": "Cancrena della Mente", "text": "Un giocatore bersaglio scarta due carte.", "type": "Stregoneria", "uuid": "088af320-a409-5095-afa2-382868abe535"}, {"flavorText": "精神攻撃の一番美しいところは、犠牲者がそれを覚えていないことだ。 ――ヴォルラス", "identifiers": {"multiverseId": "148214", "scryfallId": "edb9efcf-5a9d-4c01-8963-2c04d25dc91c"}, "language": "Japanese", "multiverseId": 148214, "name": "精神腐敗", "text": "プレイヤー１人を対象とする。そのプレイヤーはカードを２枚捨てる。", "type": "ソーサリー", "uuid": "e64238fc-d130-5e88-80ed-db6a36cf0ae9"}, {"flavorText": "\"A beleza dos ataques mentais é que suas vítimas nunca se lembram deles.\" — Volrath", "identifiers": {"multiverseId": "149709", "scryfallId": "18065976-5c85-4c6f-8601-83a001de53c0"}, "language": "Portuguese (Brazil)", "multiverseId": 149709, "name": "Estiolar a Mente", "text": "O jogador alvo descarta dois cards.", "type": "Feitiço", "uuid": "3fa5ef53-69af-5ec9-ac09-081088d27bb5"}, {"flavorText": "\"Вся прелесть промывания мозгов заключается в том, что жертва никогда о нем не помнит\". — Волрат", "identifiers": {"multiverseId": "149326", "scryfallId": "36090a4e-ef87-4df0-9723-286f6352914b"}, "language": "Russian", "multiverseId": 149326, "name": "Гниение Разума", "text": "Целевой игрок сбрасывает две карты.", "type": "Волшебство", "uuid": "7013dbe4-c71c-5c47-a824-eb8ae55774d6"}, {"flavorText": "\"La belleza de los ataques mentales es que tus víctimas nunca los recuerdan.\" —Volrath", "identifiers": {"multiverseId": "150475", "scryfallId": "9953a366-906c-4a0a-9fcb-aba2ccc8d727"}, "language": "Spanish", "multiverseId": 150475, "name": "Podredumbre mental", "text": "El jugador objetivo descarta dos cartas.", "type": "Conjuro", "uuid": "278e6f64-ad37-5329-a5d8-7aca2768c0b7"}], "frameVersion": "2003", "hasFoil": true, "hasNonFoil": true, "identifiers": {"cardKingdomFoilId": "123245", "cardKingdomId": "122877", "cardsphereFoilId": "393", "cardsphereId": "394", "deckboxId": "2100", "mcmId": "16323", "mcmMetaId": "3598", "mtgjsonV4Id": "3bbea7d5-d818-5e52-b251-a47611e9acd4", "mtgoFoilId": "27255", "mtgoId": "27254", "multiverseId": "129645", "scryfallCardBackId": "0aeebaf5-8c7d-4636-9e82-8c27447861f7", "scryfallId": "e77cb309-1fb2-451e-a96d-b02b8c99932c", "scryfallIllustrationId": "9756e56a-421c-4566-ad10-b64de3e7c06b", "scryfallOracleId": "ad44cf74-b717-48fb-9fa2-77512024d76a", "tcgplayerProductId": "15217"}, "isEtched": false, "isFoil": false, "isReprint": true, "language": "English", "layout": "normal", "legalities": {"brawl": "Legal", "commander": "Legal", "duel": "Legal", "gladiator": "Legal", "historic": "Legal", "legacy": "Legal", "modern": "Legal", "oathbreaker": "Legal", "pauper": "Legal", "paupercommander": "Legal", "penny": "Legal", "pioneer": "Legal", "predh": "Legal", "premodern": "Legal", "timeless": "Legal", "vintage": "Legal"}, "manaCost": "{2}{B}", "manaValue": 3.0, "name": "Mind Rot", "number": "159", "originalText": "Target player discards two cards.", "printings": ["10E", "7ED", "8ED", "9ED", "DPA", "DTK", "KLD", "KLR", "M10", "M11", "M12", "M13", "M14", "M15", "M19", "M20", "M21", "ORI", "P02", "PLST", "POR", "PS11", "RTR", "S99", "W16"], "purchaseUrls": {"cardKingdom": "https://mtgjson.com/links/9fe52a154295d1c2", "cardKingdomFoil": "https://mtgjson.com/links/9a81ca865abec464", "cardmarket": "https://mtgjson.com/links/945639e0e1caf4dc", "tcgplayer": "https://mtgjson.com/links/614b87141a858c01"}, "rarity": "common", "setCode": "10E", "sourceProducts": {"foil": ["c5cd29de-5ec9-5e13-b8eb-40e3a9f79f9a", "c690e178-661d-5e17-9b29-a5bf6319a844"], "nonfoil": ["3f1c2aba-e5f1-5ef8-8fd8-f5942fbd5aff", "4831adbb-c0af-5d27-b407-19f2f7805949", "c690e178-661d-5e17-9b29-a5bf6319a844", "ff67afca-f016-5399-83b0-9f9f6e14f950"]}, "subtypes": [], "supertypes": [], "text": "Target player discards two cards.", "type": "Sorcery", "types": ["Sorcery"], "uuid": "9ba7d620-4e3f-554d-b245-7ad70b63a746"}, {"artist": "Thomas M. Baxa", "artistIds": ["ff346569-557d-4043-ae44-97c2c7cabd7d"], "availability": ["mtgo", "paper"], "boosterTypes": ["default"], "borderColor": "black", "colorIdentity": ["B"], "colors": ["B"], "convertedManaCost": 2.0, "count": 1, "edhrecRank": 18696, "edhrecSaltiness": 0.12, "finishes": ["nonfoil"], "foreignData": [{"flavorText": "「我最爱的诅咒是慢慢生效，并以受诅心灵无法理解的方式逐渐污化之。」 ～腐沼女巫伊黎莎", "identifiers": {"multiverseId": "147697", "scryfallId": "038aca61-46a2-4118-a2ca-96b735e3dd1a"}, "language": "Chinese Simplified", "multiverseId": 147697, "name": "污化羁绊", "text": "生物结界（于使用时指定一个生物为目标。 此牌进场时结附在该生物上。）\n每当受此结界的生物进行攻击或阻挡时，此生物的操控者失去3点生命。", "type": "结界～灵气", "uuid": "3951090b-a8ec-5fc7-ac9f-8150898f3eb5"}, {"flavorText": "« Mes malédictions préférées sont celles qui se manifestent lentement, ternissant l'âme sans que la victime parvienne à le comprendre. » —Erissa, sorcière des marécages", "identifiers": {"multiverseId": "150065", "scryfallId": "2402b4dc-25e6-40ec-a6cd-f40c1e9abc50"}, "language": "French", "multiverseId": 150065, "name": "Lien contaminé", "text": "Enchanter : créature (Ciblez une créature au moment où vous jouez cette carte. Cette carte arrive en jeu attachée à cette créature.)\nÀ chaque fois que la créature enchantée attaque ou bloque, son contrôleur perd 3 points de vie.", "type": "Enchantement : aura", "uuid": "531fc409-5e9a-5b74-93b3-d010b35c501a"}, {"flavorText": "„Meine besten Verfluchungen manifestieren sich langsam und verdunkeln die Seele auf eine Art und Weise, die das Opfer niemals verstehen können wird.\" —Erissa, Sumpfhexe", "identifiers": {"multiverseId": "148463", "scryfallId": "7aad093f-b7ed-4529-bc35-0decfa8b66a4"}, "language": "German", "multiverseId": 148463, "name": "Verseuchte Verbindung", "text": "Kreaturenverzauberung (Bestimme eine Kreatur als Ziel, sowie du diese Karte spielst. Diese Karte kommt an die Kreatur angelegt ins Spiel.)\nImmer wenn die verzauberte Kreatur angreift oder blockt, verliert ihr Beherrscher 3 Lebenspunkte.", "type": "Verzauberung — Aura", "uuid": "197ac6c5-688a-55d9-8789-e522086a94a0"}, {"flavorText": "\"Le mie maledizioni preferite sono quelle che si manifestano lentamente, offuscando l'anima in un modo che la vittima non può nemmeno sperare di comprendere.\" —Erissa, fattucchiera della palude", "identifiers": {"multiverseId": "148846", "scryfallId": "af23e101-4df4-4a61-8913-6063d377bd53"}, "language": "Italian", "multiverseId": 148846, "name": "Legame Contaminato", "text": "Incanta creatura (Bersaglia una creatura mentre giochi questa carta. Questa carta entra in gioco assegnata a quella creatura.)\nOgniqualvolta la creatura incantata attacca o blocca, il suo controllore perde 3 punti vita.", "type": "Incantesimo — Aura", "uuid": "308bb0b2-ad05-534d-a6d8-00a2735bf98a"}, {"flavorText": "ゆっくりと魂を汚していって、何が起こっているかそいつにすら理解できないって呪いがお気に入りだね。 ――沼の魔女、エリッサ", "identifiers": {"multiverseId": "148080", "scryfallId": "c8d18573-d5a8-4137-a553-8e0b382be24c"}, "language": "Japanese", "multiverseId": 148080, "name": "汚染された結合", "text": "エンチャント（クリーチャー） （これをプレイする際に、クリーチャー１体を対象とする。 このカードはそのクリーチャーにつけられている状態で場に出る。）\nエンチャントされているクリーチャーが攻撃やブロックするたび、それのコントローラーは３点のライフを失う。", "type": "エンチャント — オーラ", "uuid": "b92049ad-d1ed-5252-9c8b-64ad9850104f"}, {"flavorText": "\"Minhas maldições favoritas são as que se manifestam lentamente, enegrecendo a alma de modos que a vítima não pode esperar compreender.\" — Erissa, bruxa do pântano", "identifiers": {"multiverseId": "149682", "scryfallId": "ad6211f5-11bb-4ae2-896d-88e2aae51098"}, "language": "Portuguese (Brazil)", "multiverseId": 149682, "name": "Elo Contaminado", "text": "Encantar criatura (Ao jogar este card, escolha uma criatura alvo. Este card entra em jogo anexado àquela criatura.)\nToda vez que a criatura encantada ataca ou bloqueia, o seu controlador perde 3 pontos de vida.", "type": "Encantamento — Aura", "uuid": "dbe3e12c-6120-57de-993b-d22b85976b03"}, {"flavorText": "\"Мои любимые проклятия действуют медленно, очерняя душу жертвы самыми необъяснимыми путями\". — Эрисса, болотная ведьма", "identifiers": {"multiverseId": "149299", "scryfallId": "6ddd5e42-020d-481d-a1a4-4361b449627f"}, "language": "Russian", "multiverseId": 149299, "name": "Зараженные Оковы", "text": "Зачаровать существо (При разыгрывании этой карты выберите целью существо. Эта карта входит в игру прикрепленной к тому существу.)\nКаждый раз, когда зачарованное существо атакует или блокирует, контролирующий его игрок теряет 3 жизни.", "type": "Чары — Аура", "uuid": "43a7c216-9a97-558d-8846-6ac37e1253f9"}, {"flavorText": "\"Mis maldiciones favoritas son las que se desarrollan lentamente, oscureciendo el alma de formas que la víctima no puede siquiera entender.\" —Erissa, bruja del pantano", "identifiers": {"multiverseId": "150448", "scryfallId": "868016e2-18f2-4c50-969e-607e718dc83b"}, "language": "Spanish", "multiverseId": 150448, "name": "Vínculo contaminado", "text": "Encantar criatura. (Haz objetivo a una criatura al jugarlo. Esta carta entra en juego anexada a esa criatura.)\nSiempre que la criatura encantada ataque o bloquee, su controlador pierde 3 vidas.", "type": "Encantamiento — Aura", "uuid": "e9c60499-d0e8-514d-9089-ada949a1a5d7"}], "frameVersion": "2003", "hasFoil": false, "hasNonFoil": true, "identifiers": {"cardKingdomFoilId": "123218", "cardKingdomId": "122850", "cardsphereId": "124", "deckboxId": "1949", "mcmId": "16296", "mcmMetaId": "1117", "mtgjsonFoilVersionId": "9c0311e8-03c1-527d-9d90-6fa2dba2aae9", "mtgjsonV4Id": "c5393c68-2c74-523c-93a7-f4bd53f46faa", "mtgoFoilId": "27593", "mtgoId": "27592", "multiverseId": "129590", "scryfallCardBackId": "0aeebaf5-8c7d-4636-9e82-8c27447861f7", "scryfallId": "a56b6552-367e-4b0b-9095-42322843b1b2", "scryfallIllustrationId": "455626bc-4c8c-4257-a12e-21ac7207e1fe", "scryfallOracleId": "56aeaee8-e014-485e-b7ad-e26ade663bcf", "tcgplayerProductId": "15084"}, "isEtched": false, "isFoil": false, "isReprint": true, "keywords": ["Enchant"], "language": "English", "layout": "normal", "legalities": {"commander": "Legal", "duel": "Legal", "legacy": "Legal", "modern": "Legal", "oathbreaker": "Legal", "pauper": "Legal", "paupercommander": "Legal", "penny": "Legal", "predh": "Legal", "vintage": "Legal"}, "manaCost": "{1}{B}", "manaValue": 2.0, "name": "Contaminated Bond", "number": "132", "originalText": "Enchant creature (Target a creature as you play this. This card comes into play attached to that creature.)\nWhenever enchanted creature attacks or blocks, its controller loses 3 life.", "printings": ["10E", "9ED", "MRD"], "purchaseUrls": {"cardKingdom": "https://mtgjson.com/links/7ea01025ac25673f", "cardKingdomFoil": "https://mtgjson.com/links/2870e9dc4eabfa43", "cardmarket": "https://mtgjson.com/links/ddbac221dc5dff07", "tcgplayer": "https://mtgjson.com/links/c7ee56ec6decbeeb"}, "rarity": "common", "setCode": "10E", "sourceProducts": {"nonfoil": ["3f1c2aba-e5f1-5ef8-8fd8-f5942fbd5aff", "4831adbb-c0af-5d27-b407-19f2f7805949", "c690e178-661d-5e17-9b29-a5bf6319a844"]}, "subtypes": ["Aura"], "supertypes": [], "text": "Enchant creature (Target a creature as you cast this. This card enters attached to that creature.)\nWhenever enchanted creature attacks or blocks, its controller loses 3 life.", "type": "Enchantment — Aura", "types": ["Enchantment"], "uuid": "2562f5f1-4de2-5834-a9ff-99092380d910", "variations": ["9c0311e8-03c1-527d-9d90-6fa2dba2aae9"]}, {"artist": "Nick Percival", "artistIds": ["d5dc3c78-b4d0-4e0a-8bfb-fd7b1c36a5e4"], "availability": ["mtgo", "paper"], "boosterTypes": ["default"], "borderColor": "black", "colorIdentity": ["B"], "colors": ["B"], "convertedManaCost": 3.0, "count": 1, "edhrecRank": 2614, "edhrecSaltiness": 0.55, "finishes": ["nonfoil", "foil"], "flavorText": "\"Pain is both a tool and a craft. Like any tool, it must be sharpened. Like any craft, it must be practiced.\"\n—Hooks, Cabal torturer", "foreignData": [{"flavorText": "「痛苦是工具，也是技艺。 一如工具，它得磨利。 一如技艺，它得施展。」 ～柯帮刑吏虎克", "identifiers": {"multiverseId": "147824", "scryfallId": "a55d9281-b840-42c0-a59d-f390c597aad9"}, "language": "Chinese Simplified", "multiverseId": 147824, "name": "偏头痛", "text": "每当对手弃一张牌时，偏头痛对该牌手造成2点伤害。", "type": "结界", "uuid": "0fe654be-2bc2-54c4-b26c-86edb96c91e6"}, {"flavorText": "« Cloués au sol, de honte et de céphalalgies … » — Arthur Rimbaud, Poésies", "identifiers": {"multiverseId": "150090", "scryfallId": "6d277941-b614-4a8c-8c56-c214360c7deb"}, "language": "French", "multiverseId": 150090, "name": "Céphalalgie", "text": "À chaque fois qu'un adversaire se défausse d'une carte, la Céphalalgie lui inflige 2 blessures.", "type": "Enchantement", "uuid": "1800d02d-93b9-537e-8070-a9ed72c5c9aa"}, {"flavorText": "„Schmerz ist sowohl ein Werkzeug als auch ein Handwerk. Wie jedes Werkzeug muss er immer wieder geschärft werden. Wie jedes Handwerk muss er immer wieder geübt werden.\" —Hooks, Kabbalisten-Folterknecht", "identifiers": {"multiverseId": "148590", "scryfallId": "a33b94a4-7926-4b0b-9540-5eb4caef2b2a"}, "language": "German", "multiverseId": 148590, "name": "Schwermut", "text": "Immer wenn ein Gegner eine Karte abwirft, fügt Schwermut diesem Spieler 2 Schadenspunkte zu.", "type": "Verzauberung", "uuid": "a2f4f499-429b-5766-85a9-45e7591beabd"}, {"flavorText": "\"Il dolore è sia uno strumento che un'arte. Come tutti gli strumenti, deve essere affilato. Come tutte le arti, deve essere esercitato.\" —Uncino, torturatore della Cabala", "identifiers": {"multiverseId": "148973", "scryfallId": "5bb8c373-f922-4b4d-9e25-4db177938a06"}, "language": "Italian", "multiverseId": 148973, "name": "Emicrania", "text": "Ogniqualvolta un avversario scarta una carta, l'Emicrania infligge 2 danni a quel giocatore.", "type": "Incantesimo", "uuid": "716143f8-f979-54c6-96d2-6547108d6e2e"}, {"flavorText": "苦痛は道具であり技術だ。 道具と一緒で研ぎ澄まさなくちゃいけないし、 技術と一緒で鍛えなきゃいけない。 ――陰謀団の拷問官、フックス", "identifiers": {"multiverseId": "148207", "scryfallId": "597eeda7-44dd-48eb-9cf4-b01e7b33b30f"}, "language": "Japanese", "multiverseId": 148207, "name": "偏頭痛", "text": "いずれかの対戦相手がカードを１枚捨てるたび、偏頭痛はそのプレイヤーに２点のダメージを与える。", "type": "エンチャント", "uuid": "4ec270d3-26b6-52f8-a3ab-e0a7868b2cd3"}, {"flavorText": "\"A dor é uma ferramenta e uma arte. Como qualquer ferramenta, deve ser afiada. Como qualquer arte, deve ser praticada.\" — Hooks, torturador da Cabala", "identifiers": {"multiverseId": "149707", "scryfallId": "babbe033-e2c8-47a6-96d0-9d2228e02037"}, "language": "Portuguese (Brazil)", "multiverseId": 149707, "name": "Enxaqueca", "text": "Toda vez que um oponente descarta um card, Enxaqueca causa 2 pontos de dano àquele jogador.", "type": "Encantamento", "uuid": "4dee5fd2-4800-55d6-b4c2-6a162b6fb081"}, {"flavorText": "\"Боль это и орудие, и мастерство. Как любое орудие, его надо затачивать. Как любое мастерство, его надо оттачивать\". — Хукс, мучитель Кабалов", "identifiers": {"multiverseId": "149324", "scryfallId": "4735760b-cbbe-4c26-a62b-dcbac5009076"}, "language": "Russian", "multiverseId": 149324, "name": "Мигрень", "text": "Каждый раз, когда оппонент сбрасывает карту, Мигрень наносит тому игроку 2 повреждения.", "type": "Чары", "uuid": "45a3dc79-99fc-5724-ad9c-32e6b6a967af"}, {"flavorText": "\"El dolor es tanto una herramienta como un arte. Como cualquier herramienta, debe ser afilada. Como cualquier arte, debe ser practicado.\" —Garfios, torturador de la Cábala.", "identifiers": {"multiverseId": "150473", "scryfallId": "729dfbde-0afa-4ada-bd0c-b6f45360a00c"}, "language": "Spanish", "multiverseId": 150473, "name": "Jaqueca", "text": "Siempre que un oponente descarte una carta, la Jaqueca hace 2 puntos de daño a ese jugador.", "type": "Encantamiento", "uuid": "138b959a-271c-5c50-90f5-6432805af740"}], "frameVersion": "2003", "hasFoil": true, "hasNonFoil": true, "identifiers": {"cardKingdomFoilId": "123243", "cardKingdomId": "122875", "cardsphereFoilId": "379", "cardsphereId": "380", "deckboxId": "2077", "mcmId": "16321", "mcmMetaId": "3523", "mtgjsonV4Id": "e2f680ac-6e30-5f14-b89d-2d11c68be899", "mtgoFoilId": "27688", "mtgoId": "27687", "multiverseId": "129640", "scryfallCardBackId": "0aeebaf5-8c7d-4636-9e82-8c27447861f7", "scryfallId": "13604ba3-b238-4a63-80f7-9dc2d5d04ded", "scryfallIllustrationId": "d24aca6a-25c9-4266-bfa7-ecf4063a8a0b", "scryfallOracleId": "633ad9e2-9f55-4a1c-9248-661ad4b0e1dc", "tcgplayerProductId": "15210"}, "isEtched": false, "isFoil": false, "isReprint": true, "language": "English", "layout": "normal", "legalities": {"commander": "Legal", "duel": "Legal", "legacy": "Legal", "modern": "Legal", "oathbreaker": "Legal", "predh": "Legal", "premodern": "Legal", "vintage": "Legal"}, "manaCost": "{2}{B}", "manaValue": 3.0, "name": "Megrim", "number": "157", "originalText": "Whenever an opponent discards a card, Megrim deals 2 damage to that player.", "printings": ["10E", "7ED", "8ED", "9ED", "DPA", "M10", "PS11", "STH"], "purchaseUrls": {"cardKingdom": "https://mtgjson.com/links/fcf563973f5ebf58", "cardKingdomFoil": "https://mtgjson.com/links/a974fd487d341e8a", "cardmarket": "https://mtgjson.com/links/f8f1c815fc006f18", "tcgplayer": "https://mtgjson.com/links/96876be47608a564"}, "rarity": "uncommon", "setCode": "10E", "sourceProducts": {"foil": ["c5cd29de-5ec9-5e13-b8eb-40e3a9f79f9a", "c690e178-661d-5e17-9b29-a5bf6319a844"], "nonfoil": ["3f1c2aba-e5f1-5ef8-8fd8-f5942fbd5aff", "4831adbb-c0af-5d27-b407-19f2f7805949", "c690e178-661d-5e17-9b29-a5bf6319a844"]}, "subtypes": [], "supertypes": [], "text": "Whenever an opponent discards a card, this enchantment deals 2 damage to that player.", "type": "Enchantment", "types": ["Enchantment"], "uuid": "0c960d75-fd2e-5a5a-ba78-58e10530fea0"}], "name": "Black Deck A", "planes": [], "releaseDate": "2008-05-02", "schemes": [], "sealedProductUuids": null, "sideBoard": [], "sourceSetCodes": ["10E", "LRW", "SHM"], "tokens": [], "type": "Sample Deck"}}